Workbook
Name BPC_TIME: [1]Selection!$I$11
Name DESC_CYTIME: [1]Selection!$E$21
Name DESC_ENTITY: [1]Selection!$D$13
Name DESC_FUND: [1]Selection!$D$15
Name VIEW_C_DATASRC: [1]Selection!$C$12
Name VIEW_CURRENCY: [1]Selection!$C$9

Sheet V1
A1: 整理 分类 | B1: S4 OCOA | C1: GCOA | D1: OCOA name (CN) | E1: SUN Code | F1: Stat | G1: IFRS | H1: OLD CAS | I1: FAM | J1: ILP | K1: OCOA name (EN) | L1: ETL Scope | M1: 重复次数 | N1: 仅I档有数的科目 | O1: 备注 | P1: need to follow up
A2: Investment | B2: 1000002000 | C2: 100000 | D2: 持有至到期投资-成本 | E2: 120601 | F2: Y | G2: Y | H2: NA | I2: Y | J2: NA | K2: Held to Maturity Securities-Nominal Value,FAM excl | L2: =IF(ISERROR(VLOOKUP(B2,'ETL Scope'!I:I,1,0)),"NA","ETL") -> NA | M2: =COUNTIF('Data-WK'!A:A,'V1'!B:B) -> 1 | N2: =VLOOKUP(E2,'IFRS only'!A:A,1,0) -> #N/A
A3: Investment | B3: 1000002010 | C3: 100000 | D3: 持有至到期投资-溢折价摊销 | E3: 120602 | F3: Y | G3: Y | H3: NA | I3: Y | J3: NA | K3: Held to Maturity Secur-Unamort Prem/Disc,FAM excl | L3: =IF(ISERROR(VLOOKUP(B3,'ETL Scope'!I:I,1,0)),"NA","ETL") -> NA | M3: =COUNTIF('Data-WK'!A:A,'V1'!B:B) -> 1 | N3: =VLOOKUP(E3,'IFRS only'!A:A,1,0) -> #N/A
A4: Investment | B4: 1000002020 | C4: 100000 | D4: 持有至到期投资-减值准备 | E4: 120604 | F4: Y | G4: Y | H4: NA | I4: NA | J4: NA | K4: Held to Maturity Secur-Prov for Impairment,FAMexcl | L4: =IF(ISERROR(VLOOKUP(B4,'ETL Scope'!I:I,1,0)),"NA","ETL") -> NA | M4: =COUNTIF('Data-WK'!A:A,'V1'!B:B) -> 1 | N4: =VLOOKUP(E4,'IFRS only'!A:A,1,0) -> #N/A
A5: Investment | B5: 1010000000 | C5: 101000 | D5: 可供出售金融资产-债券(IFRS) | E5: 120506 | F5: NA | G5: Y | H5: NA | I5: Y | J5: NA | K5: Bonds, Available for Sale, FAM excl | L5: =IF(ISERROR(VLOOKUP(B5,'ETL Scope'!I:I,1,0)),"NA","ETL") -> NA | M5: =COUNTIF('Data-WK'!A:A,'V1'!B:B) -> 1 | N5: =VLOOKUP(E5,'IFRS only'!A:A,1,0) -> 120506
A6: Investment | B6: 1010002000 | C6: 101000 | D6: 可供出售金融资产-债券-成本 | E6: 120501 | F6: Y | G6: Y | H6: NA | I6: Y | J6: NA | K6: Available for Sales Securities-NominalVal,FAM excl | L6: =IF(ISERROR(VLOOKUP(B6,'ETL Scope'!I:I,1,0)),"NA","ETL") -> NA | M6: =COUNTIF('Data-WK'!A:A,'V1'!B:B) -> 7 | N6: =VLOOKUP(E6,'IFRS only'!A:A,1,0) -> #N/A
A7: Investment | B7: 1010002010 | C7: 101000 | D7: 可供出售金融资产-债券-溢折价摊销 | E7: 120502 | F7: Y | G7: Y | H7: NA | I7: Y | J7: NA | K7: AFS Securities-Unamort Prem/Disc, FAM excl | L7: =IF(ISERROR(VLOOKUP(B7,'ETL Scope'!I:I,1,0)),"NA","ETL") -> NA | M7: =COUNTIF('Data-WK'!A:A,'V1'!B:B) -> 6 | N7: =VLOOKUP(E7,'IFRS only'!A:A,1,0) -> #N/A
A8: Investment | B8: 1010002020 | C8: 101000 | D8: 可供出售金融资产-债券-公允价值变动 | E8: 120504 | F8: Y | G8: Y | H8: NA | I8: Y | J8: NA | K8: AFS Securities-Mark to Market change,FAM excl | L8: =IF(ISERROR(VLOOKUP(B8,'ETL Scope'!I:I,1,0)),"NA","ETL") -> NA | M8: =COUNTIF('Data-WK'!A:A,'V1'!B:B) -> 7 | N8: =VLOOKUP(E8,'IFRS only'!A:A,1,0) -> #N/A
A9: Investment | B9: 1010002021 | C9: 101000 | D9: 可供出售金融资产-债券-公允价值变动(手工) | E9: 120504 | F9: Y | G9: NA | H9: NA | I9: NA | J9: NA | K9: AFS Securities-Mark to Market change,FAM excl | L9: =IF(ISERROR(VLOOKUP(B9,'ETL Scope'!I:I,1,0)),"NA","ETL") -> NA | M9: =COUNTIF('Data-WK'!A:A,'V1'!B:B) -> 0 | N9: =VLOOKUP(E9,'IFRS only'!A:A,1,0) -> #N/A
A10: Investment | B10: 1010002030 | C10: 101000 | D10: 可供出售金融资产-减值准备-债券 | E10: 120505 | F10: Y | G10: Y | H10: NA | I10: Y | J10: NA | K10: AFS Securities-Prov for Impairment,FAM excl | L10: =IF(ISERROR(VLOOKUP(B10,'ETL Scope'!I:I,1,0)),"NA","ETL") -> NA | M10: =COUNTIF('Data-WK'!A:A,'V1'!B:B) -> 7 | N10: =VLOOKUP(E10,'IFRS only'!A:A,1,0) -> #N/A
A11: Investment | B11: 1030000000 | C11: 103000 | D11: 公允价值选择权-债券(IFRS) | E11: 121001 | F11: NA | G11: Y | H11: NA | I11: Y | J11: NA | K11: Bonds, Fair Value Option, FAM excl | L11: =IF(ISERROR(VLOOKUP(B11,'ETL Scope'!I:I,1,0)),"NA","ETL") -> NA | M11: =COUNTIF('Data-WK'!A:A,'V1'!B:B) -> 12 | N11: =VLOOKUP(E11,'IFRS only'!A:A,1,0) -> 121001
A12: Investment | B12: 1030000010 | C12: 103000 | D12: 交易性金融资产-债券-成本-ILP | E12: 新增 | F12: Y | G12: Y | H12: NA | I12: NA | J12: Y | K12: 待Group 决定 | L12: =IF(ISERROR(VLOOKUP(B12,'ETL Scope'!I:I,1,0)),"NA","ETL") -> NA | M12: =COUNTIF('Data-WK'!A:A,'V1'!B:B) -> 0 | N12: =VLOOKUP(E12,'IFRS only'!A:A,1,0) -> #N/A
A13: Investment | B13: 1030000020 | C13: 103000 | D13: 交易性金融资产-债券-公允价值变动-ILP | E13: 12010102 | F13: Y | G13: Y | H13: NA | I13: NA | J13: Y-D | K13: 待Group 决定 | L13: =IF(ISERROR(VLOOKUP(B13,'ETL Scope'!I:I,1,0)),"NA","ETL") -> NA | M13: =COUNTIF('Data-WK'!A:A,'V1'!B:B) -> 0 | N13: =VLOOKUP(E13,'IFRS only'!A:A,1,0) -> #N/A
A14: Term Deposit | B14: 1140000000 | C14: 114000 | D14: 定期存款-1年及以上 | E14: 1204020101;1204020102;1204020103;1204020104;1204020105;1204020106;1204020107;1204020108;1204020109;1204020110;1204020111;1204020112;1204020113;1204020114;1204020115;1204020116;1204020141;1204020142;1204020143;1204020144;1204020145;1204020146;1204020147;1204020148;1204020149;1204020201;1204020202;1204020203;1204020204;1204020205;1204020206;1204020207;1204020208;1204020209;1204020210;1204020211;1204020212;1204020213;1204020214;1204020215;1204020216;1204020241;1204020242;1204020243;1204020244;1204020245;1204020246;1204020247;1204020248;1204020249;1204020301;1204020302;1204020303;1204020304;1204020305;1204020306;1204020307;1204020308;1204020309;1204020310;1204020311;1204020312;1204020313;1204020314;1204020315;1204020316;1204020341;1204020342;1204020343;1204020344;1204020345;1204020346;1204020347;1204020348;1204020349 | F14: Y | G14: Y | H14: NA | I14: Y | J14: NA | K14: Long Term Deposits>=1 year, FAM excl | L14: =IF(ISERROR(VLOOKUP(B14,'ETL Scope'!I:I,1,0)),"NA","ETL") -> NA | M14: =COUNTIF('Data-WK'!A:A,'V1'!B:B) -> 75 | N14: =VLOOKUP(E14,'IFRS only'!A:A,1,0) -> #VALUE!
A15: Term Deposit | B15: 1140002000 | C15: 114000 | D15: 存出资本保证金-1年及以上 | E15: 160102 | F15: Y | G15: Y | H15: NA | I15: NA | J15: NA | K15: Statutory Deposit, FAM excl | P15: 待Group决定
A16: Term Deposit | B16: 1140003000 | C16: 114000 | D16: 协议存款 | E16: 1204030101;1204030102;1204030103;1204030104;1204030105;1204030106;1204030107;1204030108;1204030109;1204030110;1204030111;1204030112;1204030113;1204030114;1204030115;1204030116;1204030141;1204030142;1204030143;1204030144;1204030145;1204030146;1204030147;1204030148;1204030149;1204030150;1204030151 | F16: Y | G16: Y | H16: NA | I16: NA | J16: NA | K16: 待Group 决定 | L16: =IF(ISERROR(VLOOKUP(B16,'ETL Scope'!I:I,1,0)),"NA","ETL") -> NA | M16: =COUNTIF('Data-WK'!A:A,'V1'!B:B) -> 0 | N16: =VLOOKUP(E16,'IFRS only'!A:A,1,0) -> #VALUE! | P16: 待Group决定
A17: Term Deposit | B17: 1140110000 | C17: 114011 | D17: 定期存款-1年期以下 | E17: 1204010101;1204010102;1204010103;1204010104;1204010105;1204010106;1204010107;1204010108;1204010109;1204010110;1204010111;1204010112;1204010113;1204010114;1204010115;1204010116;1204010141;1204010142;1204010143;1204010144;1204010145;1204010146;1204010147;1204010148;1204010149;1204010201;1204010202;1204010203;1204010204;1204010205;1204010206;1204010207;1204010208;1204010209;1204010210;1204010211;1204010212;1204010213;1204010214;1204010215;1204010216;1204010241;1204010242;1204010243;1204010244;1204010245;1204010247;1204010248;1204010249;1204010250;1204010251;1204010301;1204010302;1204010303;1204010304;1204010305;1204010306;1204010307;1204010308;1204010309;1204010310;1204010311;1204010312;1204010313;1204010314;1204010315;1204010341;1204010342;1204010343;1204010344;1204010345;1204010346;1204010347;1204010348;1204010349 | F17: Y | G17: Y | H17: NA | I17: Y | J17: NA | K17: Non Neg TDs > 90 days <1 year, FAM excl | L17: =IF(ISERROR(VLOOKUP(B17,'ETL Scope'!I:I,1,0)),"NA","ETL") -> NA | M17: =COUNTIF('Data-WK'!A:A,'V1'!B:B) -> 75 | N17: =VLOOKUP(E17,'IFRS only'!A:A,1,0) -> #VALUE!
A18: Investment | B18: 1143010000 | C18: 114301 | D18: 债券逆回购-1年及以上-面值 | E18: 12030101 | F18: Y | G18: Y | H18: NA | I18: Y | J18: NA | K18: Reverse Repo >=1 year, FAM excl | L18: =IF(ISERROR(VLOOKUP(B18,'ETL Scope'!I:I,1,0)),"NA","ETL") -> NA | M18: =COUNTIF('Data-WK'!A:A,'V1'!B:B) -> 1 | N18: =VLOOKUP(E18,'IFRS only'!A:A,1,0) -> #N/A
A19: Investment | B19: 1143011000 | C19: 114301 | D19: 债券逆回购-1年及以上-面值(手工) | E19: 12030101 | F19: Y | G19: Y | H19: NA | I19: NA | J19: Y | K19: Reverse Repo >=1 year | L19: =IF(ISERROR(VLOOKUP(B19,'ETL Scope'!I:I,1,0)),"NA","ETL") -> NA | M19: =COUNTIF('Data-WK'!A:A,'V1'!B:B) -> 1 | N19: =VLOOKUP(E19,'IFRS only'!A:A,1,0) -> #N/A
A20: Investment | B20: 1143110000 | C20: 114311 | D20: 债券逆回购-3个月至1年-面值 | E20: 12030101 | F20: Y | G20: Y | H20: NA | I20: Y | J20: NA | K20: Reverse Repo >90 days <1 year, FAM excl | L20: =IF(ISERROR(VLOOKUP(B20,'ETL Scope'!I:I,1,0)),"NA","ETL") -> NA | M20: =COUNTIF('Data-WK'!A:A,'V1'!B:B) -> 1 | N20: =VLOOKUP(E20,'IFRS only'!A:A,1,0) -> #N/A
A21: Investment | B21: 1143111000 | C21: 114311 | D21: 债券逆回购-3个月至1年-面值(手工) | E21: 12030101 | F21: Y | G21: Y | H21: NA | I21: Y | J21: Y | K21: Reverse Repo >90 days <1 year
A22: Investment | B22: 1240000000 | C22: 124000 | D22: 贷款及应收款项-非标投资(有抵押)-本金 | E22: 120801 | F22: Y | G22: Y | H22: NA | I22: Y | J22: NA | K22: Collateral & Guaranteed Loans, FAM excl | L22: =IF(ISERROR(VLOOKUP(B22,'ETL Scope'!I:I,1,0)),"NA","ETL") -> NA | M22: =COUNTIF('Data-WK'!A:A,'V1'!B:B) -> 1 | N22: =VLOOKUP(E22,'IFRS only'!A:A,1,0) -> #N/A
A23: Insurance cash items | B23: 1243000000 | C23: 124300 | D23: 保户质押贷款-本金 | E23: 120701 | F23: Y | G23: Y | H23: NA | I23: NA | J23: NA | K23: Policy Loans | L23: =IF(ISERROR(VLOOKUP(B23,'ETL Scope'!I:I,1,0)),"NA","ETL") -> NA | M23: =COUNTIF('Data-WK'!A:A,'V1'!B:B) -> 1 | N23: =VLOOKUP(E23,'IFRS only'!A:A,1,0) -> #N/A
A24: Investment | B24: 1245002000 | C24: 124500 | D24: 贷款及应收款项-非标投资(无抵押)-本金 | E24: 120801;120804; | F24: Y | G24: Y | H24: NA | I24: Y | J24: NA | K24: Unsecured & Non-guaranteed Loans, FAM excl | L24: =IF(ISERROR(VLOOKUP(B24,'ETL Scope'!I:I,1,0)),"NA","ETL") -> NA | M24: =COUNTIF('Data-WK'!A:A,'V1'!B:B) -> 2 | N24: =VLOOKUP(E24,'IFRS only'!A:A,1,0) -> #N/A
A25: Investment | B25: 1300000000 | C25: 130000 | D25: 交易性金融资产-股票供股权-成本-ILP | E25: 12010301;12010302;12020103 | F25: Y | G25: Y | H25: NA | I25: Y | J25: Y | K25: Derivatives Assets,Fair Value Option,FAM excl | L25: =IF(ISERROR(VLOOKUP(B25,'ETL Scope'!I:I,1,0)),"NA","ETL") -> NA | M25: =COUNTIF('Data-WK'!A:A,'V1'!B:B) -> 3 | N25: =VLOOKUP(E25,'IFRS only'!A:A,1,0) -> #N/A
A26: Investment | B26: 1410000110 | C26: 141000 | D26: 可供出售金融资产-股票-成本 | E26: 120501;120504 | F26: Y | G26: Y | H26: NA | I26: Y | J26: NA | K26: 待Group 决定 | L26: =IF(ISERROR(VLOOKUP(B26,'ETL Scope'!I:I,1,0)),"NA","ETL") -> NA | M26: =COUNTIF('Data-WK'!A:A,'V1'!B:B) -> 0 | N26: =VLOOKUP(E26,'IFRS only'!A:A,1,0) -> #N/A
A27: Investment | B27: 1410000120 | C27: 141000 | D27: 可供出售金融资产-股票-公允价值变动 | E27: 120504 | F27: Y | G27: Y | H27: NA | I27: Y | J27: NA | K27: 待Group 决定 | L27: =IF(ISERROR(VLOOKUP(B27,'ETL Scope'!I:I,1,0)),"NA","ETL") -> NA | M27: =COUNTIF('Data-WK'!A:A,'V1'!B:B) -> 0 | N27: =VLOOKUP(E27,'IFRS only'!A:A,1,0) -> #N/A
A28: Investment | B28: 1410000121 | C28: 141000 | D28: 可供出售金融资产-股票-公允价值变动(手工) | E28: 120504 | F28: Y | G28: NA | H28: NA | I28: NA | J28: NA | K28: 待Group 决定 | L28: =IF(ISERROR(VLOOKUP(B28,'ETL Scope'!I:I,1,0)),"NA","ETL") -> NA | M28: =COUNTIF('Data-WK'!A:A,'V1'!B:B) -> 0 | N28: =VLOOKUP(E28,'IFRS only'!A:A,1,0) -> #N/A
A29: Investment | B29: 1410000130 | C29: 141000 | D29: 可供出售金融资产-减值准备-股票 | E29: 120505 | F29: Y | G29: Y | H29: NA | I29: Y | J29: NA | K29: 待Group 决定
A30: Investment | B30: 1413000110 | C30: 141300 | D30: 可供出售金融资产-基金-成本 | E30: 120501;120504;120505 | F30: Y | G30: Y | H30: NA | I30: Y | J30: NA | K30: 待Group 决定 | L30: =IF(ISERROR(VLOOKUP(B30,'ETL Scope'!I:I,1,0)),"NA","ETL") -> NA | M30: =COUNTIF('Data-WK'!A:A,'V1'!B:B) -> 0 | N30: =VLOOKUP(E30,'IFRS only'!A:A,1,0) -> #N/A
A31: Investment | B31: 1413000120 | C31: 141300 | D31: 可供出售金融资产-基金-公允价值变动 | E31: 120504 | F31: Y | G31: Y | H31: NA | I31: Y | J31: NA | K31: 待Group 决定
A32: Investment | B32: 1413000121 | C32: 141300 | D32: 可供出售金融资产-基金-公允价值变动(手工) | E32: 120504 | F32: Y | G32: NA | H32: NA | I32: NA | J32: NA | K32: 待Group 决定
A33: Investment | B33: 1413000130 | C33: 141300 | D33: 可供出售金融资产-减值准备-基金 | E33: 120505 | F33: Y | G33: Y | H33: NA | I33: Y | J33: NA | K33: 待Group 决定 | L33: =IF(ISERROR(VLOOKUP(B33,'ETL Scope'!I:I,1,0)),"NA","ETL") -> NA | M33: =COUNTIF('Data-WK'!A:A,'V1'!B:B) -> 0 | N33: =VLOOKUP(E33,'IFRS only'!A:A,1,0) -> #N/A
A34: Investment | B34: 1430000000 | C34: 143000 | D34: 交易性金融资产-公允价值选择权-股票(IFRS)-ILP | E34: 121001 | F34: NA | G34: Y | H34: NA | I34: Y | J34: Y | K34: Stocks, Fair Value Option, FAM excl | L34: =IF(ISERROR(VLOOKUP(B34,'ETL Scope'!I:I,1,0)),"NA","ETL") -> NA | M34: =COUNTIF('Data-WK'!A:A,'V1'!B:B) -> 4 | N34: =VLOOKUP(E34,'IFRS only'!A:A,1,0) -> 121001
A35: Investment | B35: 1430002010 | C35: 143000 | D35: 交易性金融资产-股票-成本-ILP | E35: 12010101 | F35: Y | G35: Y | H35: NA | I35: NA | J35: Y-D | K35: 待Group 决定 | L35: =IF(ISERROR(VLOOKUP(B35,'ETL Scope'!I:I,1,0)),"NA","ETL") -> NA | M35: =COUNTIF('Data-WK'!A:A,'V1'!B:B) -> 0 | N35: =VLOOKUP(E35,'IFRS only'!A:A,1,0) -> #N/A
A36: Investment | B36: 1430002020 | C36: 143000 | D36: 交易性金融资产-股票-公允价值变动-ILP | E36: 12010102 | F36: Y | G36: Y | H36: NA | I36: NA | J36: Y-D | K36: 待Group 决定 | L36: =IF(ISERROR(VLOOKUP(B36,'ETL Scope'!I:I,1,0)),"NA","ETL") -> NA | M36: =COUNTIF('Data-WK'!A:A,'V1'!B:B) -> 0 | N36: =VLOOKUP(E36,'IFRS only'!A:A,1,0) -> #N/A
A37: Investment | B37: 1433000000 | C37: 143300 | D37: 交易性金融资产-公允价值选择权-基金(IFRS)-ILP | E37: 121001 | F37: NA | G37: Y | H37: NA | I37: Y | J37: Y | K37: Mutual Funds, Fair Value Option, FAM excl | L37: =IF(ISERROR(VLOOKUP(B37,'ETL Scope'!I:I,1,0)),"NA","ETL") -> NA | M37: =COUNTIF('Data-WK'!A:A,'V1'!B:B) -> 3 | N37: =VLOOKUP(E37,'IFRS only'!A:A,1,0) -> 121001
A38: Investment | B38: 1433000010 | C38: 143300 | D38: 交易性金融资产-基金-成本-ILP | E38: 新增 | F38: Y | G38: Y | H38: NA | I38: NA | J38: Y | K38: 待Group 决定 | L38: =IF(ISERROR(VLOOKUP(B38,'ETL Scope'!I:I,1,0)),"NA","ETL") -> NA | M38: =COUNTIF('Data-WK'!A:A,'V1'!B:B) -> 0 | N38: =VLOOKUP(E38,'IFRS only'!A:A,1,0) -> #N/A
A39: Investment | B39: 1433000020 | C39: 143300 | D39: 交易性金融资产-基金-公允价值变动-ILP | E39: 12010102 | F39: Y | G39: Y | H39: NA | I39: NA | J39: Y-D | K39: 待Group 决定 | L39: =IF(ISERROR(VLOOKUP(B39,'ETL Scope'!I:I,1,0)),"NA","ETL") -> NA | M39: =COUNTIF('Data-WK'!A:A,'V1'!B:B) -> 0 | N39: =VLOOKUP(E39,'IFRS only'!A:A,1,0) -> #N/A
A40: Investment | B40: 1444000000 | C40: 144400 | D40: 可供出售金融资产-货币基金(存款)-成本 | E40: 120501 | F40: Y | G40: Y | H40: NA | I40: Y | J40: NA | K40: Money Market Funds (Deposits), FAM excl | L40: =IF(ISERROR(VLOOKUP(B40,'ETL Scope'!I:I,1,0)),"NA","ETL") -> NA | M40: =COUNTIF('Data-WK'!A:A,'V1'!B:B) -> 1 | N40: =VLOOKUP(E40,'IFRS only'!A:A,1,0) -> #N/A
A41: Investment | B41: 1444100000 | C41: 144410 | D41: 可供出售金融资产-货币基金(现金等价物)-成本 | E41: 120501 | F41: Y | G41: Y | H41: NA | I41: Y | J41: NA | K41: Money Market Funds (Cash & Cash Equiv), FAM excl | L41: =IF(ISERROR(VLOOKUP(B41,'ETL Scope'!I:I,1,0)),"NA","ETL") -> NA | M41: =COUNTIF('Data-WK'!A:A,'V1'!B:B) -> 1 | N41: =VLOOKUP(E41,'IFRS only'!A:A,1,0) -> #N/A
A42: Investment | B42: 1444101500 | C42: 144410 | D42: 交易性金融资产-货币基金(现金等价物)-成本-ILP | E42: 新增 | F42: Y | G42: Y | H42: NA | I42: NA | J42: Y | K42: Money Market Funds (Cash & Cash Equi.) | L42: =IF(ISERROR(VLOOKUP(B42,'ETL Scope'!I:I,1,0)),"NA","ETL") -> NA | M42: =COUNTIF('Data-WK'!A:A,'V1'!B:B) -> 1 | N42: =VLOOKUP(E42,'IFRS only'!A:A,1,0) -> #N/A
A43: Fix asset & Intangible assets | B43: 2011100000 | C43: 201110 | D43: 计算机及辅助设备-原值 | E43: 16020401 | F43: Y | G43: Y | H43: NA | I43: NA | J43: NA | K43: Other F.A., Computer HW,Costs - Allocation | L43: =IF(ISERROR(VLOOKUP(B43,'ETL Scope'!I:I,1,0)),"NA","ETL") -> NA | M43: =COUNTIF('Data-WK'!A:A,'V1'!B:B) -> 1 | N43: =VLOOKUP(E43,'IFRS only'!A:A,1,0) -> #N/A
A44: Fix asset & Intangible assets | B44: 2011100030 | C44: 201110 | D44: 融资租入固定资产-原值 | E44: 16020701 | F44: Y | G44: Y | H44: NA | I44: NA | J44: NA | K44: Other Fixed Assets, F&E, Costs - Allocation | L44: =IF(ISERROR(VLOOKUP(B44,'ETL Scope'!I:I,1,0)),"NA","ETL") -> NA | M44: =COUNTIF('Data-WK'!A:A,'V1'!B:B) -> 1 | N44: =VLOOKUP(E44,'IFRS only'!A:A,1,0) -> #N/A
... A49: Fix asset & Intangible assets | B49: 2014100000 | C49: 201410 | D49: 机械及动力设备-原值 | E49: 16020201 | F49: Y | G49: Y | H49: NA | I49: NA | J49: NA | K49: Other Fixed Assets, F&E, Costs - Allocation | L49: =IF(ISERROR(VLOOKUP(B49,'ETL Scope'!I:I,1,0)),"NA","ETL") -> NA | M49: =COUNTIF('Data-WK'!A:A,'V1'!B:B) -> 1 | N49: =VLOOKUP(E49,'IFRS only'!A:A,1,0) -> #N/A
A50: Fix asset & Intangible assets | B50: 2014100010 | C50: 201410 | D50: 长期待摊-家具-原值 | E50: 新增 | F50: Y | G50: Y | H50: NA | I50: NA | J50: NA | L50: NA
A51: Fix asset & Intangible assets | B51: 2014100030 | C51: 201410 | D51: 办公设备-原值 | E51: 16020501 | F51: Y | G51: Y | H51: NA | I51: NA | J51: NA | K51: Other Fixed Assets, F&E, Costs - Allocation | L51: =IF(ISERROR(VLOOKUP(B51,'ETL Scope'!I:I,1,0)),"NA","ETL") -> NA | M51: =COUNTIF('Data-WK'!A:A,'V1'!B:B) -> 1 | N51: =VLOOKUP(E51,'IFRS only'!A:A,1,0) -> #N/A
A52: Fix asset & Intangible assets | B52: 2014200000 | C52: 201420 | D52: 机械及动力设备-累计折旧 | E52: 16020202 | F52: Y | G52: Y | H52: NA | I52: NA | J52: NA | K52: Other Fixed Assets, F&E, AccDep - Allocation | L52: =IF(ISERROR(VLOOKUP(B52,'ETL Scope'!I:I,1,0)),"NA","ETL") -> NA | M52: =COUNTIF('Data-WK'!A:A,'V1'!B:B) -> 1 | N52: =VLOOKUP(E52,'IFRS only'!A:A,1,0) -> #N/A
A53: Fix asset & Intangible assets | B53: 2014200010 | C53: 201420 | D53: 长期待摊-家具-累计摊销 | E53: 新增 | F53: Y | G53: Y | H53: NA | I53: NA | J53: NA | L53: NA
A54: Fix asset & Intangible assets | B54: 2014200030 | C54: 201420 | D54: 办公设备-累计折旧 | E54: 16020502 | F54: Y | G54: Y | H54: NA | I54: NA | J54: NA | K54: Other Fixed Assets, F&E, AccDep - Allocation | L54: =IF(ISERROR(VLOOKUP(B54,'ETL Scope'!I:I,1,0)),"NA","ETL") -> NA | M54: =COUNTIF('Data-WK'!A:A,'V1'!B:B) -> 1 | N54: =VLOOKUP(E54,'IFRS only'!A:A,1,0) -> #N/A
A55: Fix asset & Intangible assets | B55: 2016100000 | C55: 201610 | D55: 长期待摊-租赁房屋装修-原值 | E55: 16050101 | F55: Y | G55: Y | H55: NA | I55: NA | J55: NA | K55: Leasehold improvements, Costs - Allocation | L55: =IF(ISERROR(VLOOKUP(B55,'ETL Scope'!I:I,1,0)),"NA","ETL") -> NA | M55: =COUNTIF('Data-WK'!A:A,'V1'!B:B) -> 1 | N55: =VLOOKUP(E55,'IFRS only'!A:A,1,0) -> #N/A
A56: Fix asset & Intangible assets | B56: 2016200000 | C56: 201620 | D56: 长期待摊-租赁房屋装修-累计摊销 | E56: 16050102 | F56: Y | G56: Y | H56: NA | I56: NA | J56: NA | K56: Leasehold improvements, AccDep - Allocation | L56: =IF(ISERROR(VLOOKUP(B56,'ETL Scope'!I:I,1,0)),"NA","ETL") -> NA | M56: =COUNTIF('Data-WK'!A:A,'V1'!B:B) -> 1 | N56: =VLOOKUP(E56,'IFRS only'!A:A,1,0) -> #N/A
A57: Fix asset & Intangible assets | B57: 2019100000 | C57: 201910 | D57: 在建工程-租赁房屋装修 | E57: 16030101 | F57: Y | G57: Y | H57: NA | I57: NA | J57: NA | K57: Non IT FA/gen-Construction in Progress | L57: =IF(ISERROR(VLOOKUP(B57,'ETL Scope'!I:I,1,0)),"NA","ETL") -> NA | M57: =COUNTIF('Data-WK'!A:A,'V1'!B:B) -> 1 | N57: =VLOOKUP(E57,'IFRS only'!A:A,1,0) -> #N/A
A58: Others | B58: 2201000000 | C58: 220100 | D58: 递延保单获取成本(IFRS) | E58: 160001 | F58: NA | G58: Y / ETL Scope | H58: NA | I58: NA | J58: NA | K58: Deferred Acq/Orig Costs, DiRect | L58: =IF(ISERROR(VLOOKUP(B58,'ETL Scope'!I:I,1,0)),"NA","ETL") -> ETL | M58: =COUNTIF('Data-WK'!A:A,'V1'!B:B) -> 1 | N58: =VLOOKUP(E58,'IFRS only'!A:A,1,0) -> 160001
A59: Others | B59: 2201000010 | C59: 220100 | D59: 递延保单获取成本-影子调整(IFRS) | E59: 160005 | F59: NA | G59: Y / ETL Scope | H59: NA | I59: NA | J59: NA | K59: Deferred Acq/Orig Costs, DiRect, Shadow Adj. | L59: =IF(ISERROR(VLOOKUP(B59,'ETL Scope'!I:I,1,0)),"NA","ETL") -> ETL | M59: =COUNTIF('Data-WK'!A:A,'V1'!B:B) -> 1 | N59: =VLOOKUP(E59,'IFRS only'!A:A,1,0) -> 160005
A60: Others | B60: 2201000030 | C60: 220100 | D60: 递延保单获取成本-未赚佣金(IFRS) | E60: 160003 | F60: NA | G60: Y / ETL Scope | H60: NA | I60: NA | J60: NA | K60: UNEARNED COMMISSION | L60: =IF(ISERROR(VLOOKUP(B60,'ETL Scope'!I:I,1,0)),"NA","ETL") -> ETL | M60: =COUNTIF('Data-WK'!A:A,'V1'!B:B) -> 1 | N60: =VLOOKUP(E60,'IFRS only'!A:A,1,0) -> 160003
A61: Others | B61: 2201200030 | C61: 220120 | D61: 递延保单获取成本-分保未赚佣金(IFRS) | E61: 160004 | F61: NA | G61: Y / ETL Scope | H61: NA | I61: NA | J61: NA | K61: UNEARNED COMM OUTWARD REINSURANCE | L61: =IF(ISERROR(VLOOKUP(B61,'ETL Scope'!I:I,1,0)),"NA","ETL") -> ETL | M61: =COUNTIF('Data-WK'!A:A,'V1'!B:B) -> 1 | N61: =VLOOKUP(E61,'IFRS only'!A:A,1,0) -> 160004
A62: Others | B62: 2201300000 | C62: 220130 | D62: 递延保单获取成本-花旗签约费(IFRS) | E62: 160007 | F62: NA | G62: Y / ETL Scope | H62: NA | I62: NA | J62: NA | K62: Deferred Acq/Orig Costs, Access Fee, Direct | L62: =IF(ISERROR(VLOOKUP(B62,'ETL Scope'!I:I,1,0)),"NA","ETL") -> ETL | M62: =COUNTIF('Data-WK'!A:A,'V1'!B:B) -> 1 | N62: =VLOOKUP(E62,'IFRS only'!A:A,1,0) -> 160007
A63: Others | B63: 2201400000 | C63: 220140 | D63: 递延保单获取成本-花旗服务费(IFRS) | E63: 160008 | F63: NA | G63: Y / ETL Scope | H63: NA | I63: NA | J63: NA | K63: Deferred Acq/Orig Costs, Service Fee, Direct | L63: =IF(ISERROR(VLOOKUP(B63,'ETL Scope'!I:I,1,0)),"NA","ETL") -> ETL | M63: =COUNTIF('Data-WK'!A:A,'V1'!B:B) -> 1 | N63: =VLOOKUP(E63,'IFRS only'!A:A,1,0) -> 160008
A64: Others | B64: 2203000000 | C64: 220300 | D64: 待摊大额奖金(IFRS) | E64: 160002 | F64: NA | G64: Y / ETL Scope | H64: NA | I64: NA | J64: NA | K64: Deferred Sales Inducement | L64: =IF(ISERROR(VLOOKUP(B64,'ETL Scope'!I:I,1,0)),"NA","ETL") -> ETL | M64: =COUNTIF('Data-WK'!A:A,'V1'!B:B) -> 1 | N64: =VLOOKUP(E64,'IFRS only'!A:A,1,0) -> 160002
A65: Others | B65: 2203000010 | C65: 220300 | D65: 待摊大额奖金-影子调整(IFRS) | E65: 160006 | F65: NA | G65: Y / ETL Scope | H65: NA | I65: NA | J65: NA | K65: Deferred Sales Inducement, Shadow Adj. | L65: =IF(ISERROR(VLOOKUP(B65,'ETL Scope'!I:I,1,0)),"NA","ETL") -> ETL | M65: =COUNTIF('Data-WK'!A:A,'V1'!B:B) -> 1 | N65: =VLOOKUP(E65,'IFRS only'!A:A,1,0) -> 160006
... A72: Fix asset & Intangible assets | B72: 2212200040 | C72: 223101 | D72: 软件使用权-累计摊销 | E72: 16040502;16040512 | F72: Y | G72: Y | H72: NA | I72: NA | J72: NA | K72: Purchase/int'nal generate PCsoft're(IA)AccDep-Allo | L72: =IF(ISERROR(VLOOKUP(B72,'ETL Scope'!I:I,1,0)),"NA","ETL") -> NA | M72: =COUNTIF('Data-WK'!A:A,'V1'!B:B) -> 0 | N72: =VLOOKUP(E72,'IFRS only'!A:A,1,0) -> #N/A
A73: Fix asset & Intangible assets | B73: 2231010000 | C73: 223101 | D73: 长期待摊-俱乐部会员费-累计摊销 | E73: 16050202 | F73: Y | G73: Y | H73: NA | I73: NA | J73: NA | K73: Other Intangible Assets, AccDep - Allocation | L73: =IF(ISERROR(VLOOKUP(B73,'ETL Scope'!I:I,1,0)),"NA","ETL") -> NA | M73: =COUNTIF('Data-WK'!A:A,'V1'!B:B) -> 1 | N73: =VLOOKUP(E73,'IFRS only'!A:A,1,0) -> #N/A
A74: Fix asset & Intangible assets | B74: 2231110010 | C74: 223111 | D74: 长期待摊-花旗签约费-累计摊销(IFRS) | E74: 16050502 | F74: NA | G74: Y | H74: NA | I74: NA | J74: NA | K74: Intangible assets, Access Fee, Accum amortization | L74: =IF(ISERROR(VLOOKUP(B74,'ETL Scope'!I:I,1,0)),"NA","ETL") -> NA | M74: =COUNTIF('Data-WK'!A:A,'V1'!B:B) -> 1 | N74: =VLOOKUP(E74,'IFRS only'!A:A,1,0) -> 16050502
A75: Insurance cash items | B75: 2500000006 | C75: 250000 | D75: 应收保费-财务 | E75: 130402 | F75: Y | G75: Y | H75: NA | I75: NA | J75: NA | K75: Insurance receivable - LS/Reg Adj. | L75: =IF(ISERROR(VLOOKUP(B75,'ETL Scope'!I:I,1,0)),"NA","ETL") -> NA | M75: =COUNTIF('Data-WK'!A:A,'V1'!B:B) -> 1 | N75: =VLOOKUP(E75,'IFRS only'!A:A,1,0) -> #N/A
A76: Insurance cash items | B76: 2500000010 | C76: 250000 | D76: 应收保费-3个月及以内 | E76: 13040101 | F76: Y | G76: NA | H76: NA | I76: NA | J76: NA | K76: Due Premium | L76: =IF(ISERROR(VLOOKUP(B76,'ETL Scope'!I:I,1,0)),"NA","ETL") -> NA | M76: =COUNTIF('Data-WK'!A:A,'V1'!B:B) -> 1 | N76: =VLOOKUP(E76,'IFRS only'!A:A,1,0) -> #N/A
A77: Insurance cash items | B77: 2500000020 | C77: 250000 | D77: 应收保费-3个月至小于等于6个月 | E77: 13040102 | F77: Y | G77: NA | H77: NA | I77: NA | J77: NA | K77: Due Premium
A78: Insurance cash items | B78: 2500000030 | C78: 250000 | D78: 应收保费-6个月至小于等于1年 | E78: 13040104 | F78: Y | G78: NA | H78: NA | I78: NA | J78: NA | K78: Due Premium
A79: Insurance cash items | B79: 2500000040 | C79: 250000 | D79: 应收保费-1年以上 | E79: 13040103 | F79: Y | G79: NA | H79: NA | I79: NA | J79: NA | K79: Due Premium
A80: Others | B80: 2501000000 | C80: 250100 | D80: 其他应收款-保险-退保营销员佣金 | E80: 13060101 | F80: Y | G80: Y | H80: NA | I80: NA | J80: NA | K80: Agent's related Receivables | L80: =IF(ISERROR(VLOOKUP(B80,'ETL Scope'!I:I,1,0)),"NA","ETL") -> NA | M80: =COUNTIF('Data-WK'!A:A,'V1'!B:B) -> 1 | N80: =VLOOKUP(E80,'IFRS only'!A:A,1,0) -> #N/A
A81: Others | B81: 2501000001 | C81: 250100 | D81: 其他应收款-保险-退保手续费 | E81: 13060102 | F81: Y | G81: Y | H81: NA | I81: NA | J81: NA | K81: Agent's related Receivables | L81: =IF(ISERROR(VLOOKUP(B81,'ETL Scope'!I:I,1,0)),"NA","ETL") -> NA | M81: =COUNTIF('Data-WK'!A:A,'V1'!B:B) -> 1 | N81: =VLOOKUP(E81,'IFRS only'!A:A,1,0) -> #N/A
A82: Others | B82: 2501000002 | C82: 250100 | D82: 其他应收款-保险-冷静期退保员工单佣金 | E82: 13060103 | F82: Y | G82: Y | H82: NA | I82: NA | J82: NA | K82: Agent's related Receivables | L82: =IF(ISERROR(VLOOKUP(B82,'ETL Scope'!I:I,1,0)),"NA","ETL") -> NA | M82: =COUNTIF('Data-WK'!A:A,'V1'!B:B) -> 1 | N82: =VLOOKUP(E82,'IFRS only'!A:A,1,0) -> #N/A
A83: Insurance cash items | B83: 2511001500 | C83: 251100 | D83: 应收分保账款-摊回赔付支出 | E83: 130502 | F83: Y | G83: Y | H83: NA | I83: NA | J83: NA | K83: Reinsurance Claims Recoverable | L83: =IF(ISERROR(VLOOKUP(B83,'ETL Scope'!I:I,1,0)),"NA","ETL") -> NA | M83: =COUNTIF('Data-WK'!A:A,'V1'!B:B) -> 1 | N83: =VLOOKUP(E83,'IFRS only'!A:A,1,0) -> #N/A
A84: Insurance cash items | B84: 2511001501 | C84: 251100 | D84: 应收分保账款-摊回分保费用 | E84: 130503 | F84: Y | G84: Y | H84: NA | I84: NA | J84: NA | K84: Reinsurance Claims Recoverable | L84: =IF(ISERROR(VLOOKUP(B84,'ETL Scope'!I:I,1,0)),"NA","ETL") -> NA | M84: =COUNTIF('Data-WK'!A:A,'V1'!B:B) -> 1 | N84: =VLOOKUP(E84,'IFRS only'!A:A,1,0) -> #N/A
A85: Insurance cash items | B85: 2511001502 | C85: 251100 | D85: 应收分保账款-纯益手续费 | E85: 130504 | F85: Y | G85: Y | H85: NA | I85: NA | J85: NA | K85: Reinsurance Claims Recoverable | L85: =IF(ISERROR(VLOOKUP(B85,'ETL Scope'!I:I,1,0)),"NA","ETL") -> NA | M85: =COUNTIF('Data-WK'!A:A,'V1'!B:B) -> 1 | N85: =VLOOKUP(E85,'IFRS only'!A:A,1,0) -> #N/A
A86: Others | B86: 2520000000 | C86: 252000 | D86: 其他应收款-日常-其他应收 | E86: 13060304 | F86: Y | G86: Y | H86: NA | I86: NA | J86: NA | K86: Receivables, Intercompany | L86: =IF(ISERROR(VLOOKUP(B86,'ETL Scope'!I:I,1,0)),"NA","ETL") -> NA | M86: =COUNTIF('Data-WK'!A:A,'V1'!B:B) -> 0 | N86: =VLOOKUP(E86,'IFRS only'!A:A,1,0) -> #N/A
A87: Others | B87: 2520001600 | C87: 252000 | D87: 内部往来-所得税 | E87: 150401;150402;150403;15040401;15040412;150405;150406;15040701 | F87: Y | G87: Y | H87: NA | I87: NA | J87: NA | K87: Receivables, Intercompany
A88: Others | B88: 2520001700 | C88: 252000 | D88: 内部往来-日常 | E88: 150101;150102;150103;15010401;150105;150106;15010701 | F88: Y | G88: Y | H88: NA | I88: NA | J88: NA | K88: Receivables, Intercompany | L88: =IF(ISERROR(VLOOKUP(B88,'ETL Scope'!I:I,1,0)),"NA","ETL") -> NA | M88: =COUNTIF('Data-WK'!A:A,'V1'!B:B) -> 0 | N88: =VLOOKUP(E88,'IFRS only'!A:A,1,0) -> #N/A
A89: Others | B89: 2520001710 | C89: 252000 | D89: 内部往来-日常-省内 | E89: 15010402;15010403;15010404;15010405;15010406;15010407;15010408;15010409;15010410;15010411;15010412;15010413;15010414;15010702;15010703;15010704;15010705;15010706;15010707;15010708;15010709;15010710;15010711;15010712 | F89: Y | G89: Y | H89: NA | I89: NA | J89: NA | K89: Receivables, Intercompany
A90: Others | B90: 2520001800 | C90: 252000 | D90: 内部往来-保险 | E90: 150501;150502;150503;15050401;15050402;15050403;15050404;15050405;15050406;15050407;15050408;15050409;15050410;15050411;15050412;15050413;15050414;150505;150506;15050701;15050702;15050703;15050704;15050705;15050706;15050707;15050708;15050709;15050710;15050711;15050712 | F90: Y | G90: Y | H90: NA | I90: NA | J90: NA | K90: Receivables, Intercompany | L90: =IF(ISERROR(VLOOKUP(B90,'ETL Scope'!I:I,1,0)),"NA","ETL") -> NA | M90: =COUNTIF('Data-WK'!A:A,'V1'!B:B) -> 0 | N90: =VLOOKUP(E90,'IFRS only'!A:A,1,0) -> #VALUE!
A91: Others | B91: 2520001900 | C91: 252000 | D91: 内部往来-关联方 | E91: 150301;150303;150304;150305;150306;150307;150311;150312;150314;150316 | F91: Y | G91: Y | H91: NA | I91: NA | J91: NA | K91: Receivables, Intercompany | L91: =IF(ISERROR(VLOOKUP(B91,'ETL Scope'!I:I,1,0)),"NA","ETL") -> NA | M91: =COUNTIF('Data-WK'!A:A,'V1'!B:B) -> 0 | N91: =VLOOKUP(E91,'IFRS only'!A:A,1,0) -> #N/A
A92: Others | B92: 2530301500 | C92: 253030 | D92: 其他应收款-投资-证券清算款 | E92: 13060401 | F92: Y | G92: Y | H92: NA | I92: Y | J92: Y | K92: Receivables, from Sales of Investments
A93: Others | B93: 2530301501 | C93: 253030 | D93: 其他应收款-投资-证券清算款(手工) | E93: 13060401 | F93: Y | G93: Y | H93: NA | I93: NA | J93: Y | K93: Receivables, from Sales of Investments
A94: Insurance cash items | B94: 2530400050 | C94: 253040 | D94: 其他应收款-保险-暂存代收保费 | E94: 13060105 | F94: Y | G94: Y | H94: NA | I94: NA | J94: NA | K94: Other receivable - Misc Receivable | L94: =IF(ISERROR(VLOOKUP(B94,'ETL Scope'!I:I,1,0)),"NA","ETL") -> NA | M94: =COUNTIF('Data-WK'!A:A,'V1'!B:B) -> 1 | N94: =VLOOKUP(E94,'IFRS only'!A:A,1,0) -> #N/A
A95: 新增 | B95: 2530400550 | C95: 253040 | D95: 应收股利-股权股利 | E95: 130102 | F95: Y | G95: Y | H95: NA | I95: Y | J95: NA | K95: Receivables, Others, Return on Capital, FAM, OIM
A96: Insurance cash items | B96: 2530401500 | C96: 253040 | D96: 其他应收款-保险-营销员挪用垫付 | E96: 13060110 | F96: Y | G96: Y | H96: NA | I96: NA | J96: NA | K96: Other receivables | L96: =IF(ISERROR(VLOOKUP(B96,'ETL Scope'!I:I,1,0)),"NA","ETL") -> NA | M96: =COUNTIF('Data-WK'!A:A,'V1'!B:B) -> 1 | N96: =VLOOKUP(E96,'IFRS only'!A:A,1,0) -> #N/A
A97: Others | B97: 2530401501 | C97: 253040 | D97: 其他应收款-保险-其他应收 | E97: 13060106 | F97: Y | G97: Y | H97: NA | I97: NA | J97: NA | K97: Other receivables | L97: =IF(ISERROR(VLOOKUP(B97,'ETL Scope'!I:I,1,0)),"NA","ETL") -> NA | M97: =COUNTIF('Data-WK'!A:A,'V1'!B:B) -> 1 | N97: =VLOOKUP(E97,'IFRS only'!A:A,1,0) -> #N/A
A98: Others | B98: 2530401502 | C98: 253040 | D98: 其他应收款-保险-申购/赎回-ILP | E98: 13060108 | F98: Y | G98: Y | H98: NA | I98: NA | J98: Y | K98: Other receivables | L98: =IF(ISERROR(VLOOKUP(B98,'ETL Scope'!I:I,1,0)),"NA","ETL") -> NA | M98: =COUNTIF('Data-WK'!A:A,'V1'!B:B) -> 1 | N98: =VLOOKUP(E98,'IFRS only'!A:A,1,0) -> #N/A
A99: Others | B99: 2530401503 | C99: 253040 | D99: 其他应收款-日常-员工借款 | E99: 13060302 | F99: Y | G99: Y | H99: NA | I99: NA | J99: NA | K99: Other receivables | L99: =IF(ISERROR(VLOOKUP(B99,'ETL Scope'!I:I,1,0)),"NA","ETL") -> NA | M99: =COUNTIF('Data-WK'!A:A,'V1'!B:B) -> 1 | N99: =VLOOKUP(E99,'IFRS only'!A:A,1,0) -> #N/A
A100: Others | B100: 2530401504 | C100: 253040 | D100: 其他应收款-日常- RCE办公室 | E100: 13060309 | F100: Y | G100: Y | H100: NA | I100: NA | J100: NA | K100: Other receivables | L100: =IF(ISERROR(VLOOKUP(B100,'ETL Scope'!I:I,1,0)),"NA","ETL") -> NA | M100: =COUNTIF('Data-WK'!A:A,'V1'!B:B) -> 1 | N100: =VLOOKUP(E100,'IFRS only'!A:A,1,0) -> #N/A
A101: Others | B101: 2530401505 | C101: 253040 | D101: 其他应收款-投资-其他应收 | E101: 13060402 | F101: Y | G101: Y | H101: NA | I101: NA | J101: NA | K101: Other receivables | L101: =IF(ISERROR(VLOOKUP(B101,'ETL Scope'!I:I,1,0)),"NA","ETL") -> NA | M101: =COUNTIF('Data-WK'!A:A,'V1'!B:B) -> 1 | N101: =VLOOKUP(E101,'IFRS only'!A:A,1,0) -> #N/A
A102: Others | B102: 2530401508 | C102: 253040 | D102: 其他应收款-日常-银行暂挂款 | E102: 13060501 | F102: Y | G102: Y | H102: NA | I102: NA | J102: NA | K102: Other receivables | L102: =IF(ISERROR(VLOOKUP(B102,'ETL Scope'!I:I,1,0)),"NA","ETL") -> NA | M102: =COUNTIF('Data-WK'!A:A,'V1'!B:B) -> 1 | N102: =VLOOKUP(E102,'IFRS only'!A:A,1,0) -> #N/A
A103: Insurance cash items | B103: 2530600010 | C103: 253060 | D103: 其他应收款-保险-SPUL再保 | E103: 13060111 | F103: Y | G103: Y | H103: NA | I103: NA | J103: NA | K103: Financial Reinsurance Receivables | L103: =IF(ISERROR(VLOOKUP(B103,'ETL Scope'!I:I,1,0)),"NA","ETL") -> NA | M103: =COUNTIF('Data-WK'!A:A,'V1'!B:B) -> 1 | N103: =VLOOKUP(E103,'IFRS only'!A:A,1,0) -> #N/A
A104: Investment | B104: 2600000000 | C104: 260000 | D104: 应收利息(IFRS) | E104: 130315 | F104: NA | G104: Y | H104: NA | I104: Y | J104: NA | K104: Accrued Investments Income,Interest, FAM excl | L104: =IF(ISERROR(VLOOKUP(B104,'ETL Scope'!I:I,1,0)),"NA","ETL") -> NA | M104: =COUNTIF('Data-WK'!A:A,'V1'!B:B) -> 1 | N104: =VLOOKUP(E104,'IFRS only'!A:A,1,0) -> 130315
A105: Investment | B105: 2600000020 | C105: 260000 | D105: 应收利息-3个月以内定期存款-ILP | E105: 130301 | F105: Y | G105: Y | H105: NA | I105: NA | J105: Y | K105: Accrued Investments Income, Interest | L105: =IF(ISERROR(VLOOKUP(B105,'ETL Scope'!I:I,1,0)),"NA","ETL") -> NA | M105: =COUNTIF('Data-WK'!A:A,'V1'!B:B) -> 1 | N105: =VLOOKUP(E105,'IFRS only'!A:A,1,0) -> #N/A
A106: Investment | B106: 2600000030 | C106: 260000 | D106: 应收利息-保户质押贷款 | E106: 130310 | F106: Y | G106: Y | H106: NA | I106: NA | J106: NA | K106: Accrued Investments Income, Interest | L106: =IF(ISERROR(VLOOKUP(B106,'ETL Scope'!I:I,1,0)),"NA","ETL") -> NA | M106: =COUNTIF('Data-WK'!A:A,'V1'!B:B) -> 1 | N106: =VLOOKUP(E106,'IFRS only'!A:A,1,0) -> #N/A
A107: Investment | B107: 2600000100 | C107: 260000 | D107: 应收利息-活期存款-ILP | E107: 130313 | F107: Y | G107: Y | H107: NA | I107: NA | J107: Y | K107: Accrued Investments Income, Interest | L107: =IF(ISERROR(VLOOKUP(B107,'ETL Scope'!I:I,1,0)),"NA","ETL") -> NA | M107: =COUNTIF('Data-WK'!A:A,'V1'!B:B) -> 1 | N107: =VLOOKUP(E107,'IFRS only'!A:A,1,0) -> #N/A
... A116: Investment | B116: 2600002110 | C116: 260000 | D116: 应收利息-3个月以内定期存款 | E116: 130301 | F116: Y | G116: Y | H116: NA | I116: NA | J116: NA | K116: 待Group 决定 | L116: =IF(ISERROR(VLOOKUP(B116,'ETL Scope'!I:I,1,0)),"NA","ETL") -> NA | M116: =COUNTIF('Data-WK'!A:A,'V1'!B:B) -> 0 | N116: =VLOOKUP(E116,'IFRS only'!A:A,1,0) -> #N/A
A117: Investment | B117: 2600002120 | C117: 260000 | D117: 应收利息-协议存款 | E117: 130306 | F117: Y | G117: Y | H117: NA | I117: NA | J117: NA | K117: 待Group 决定
A118: Investment | B118: 2600002130 | C118: 260000 | D118: 应收利息-存出资本保证金 | E118: 130312 | F118: Y | G118: Y | H118: NA | I118: NA | J118: NA | K118: 待Group 决定
...

Sheet Sheet1
A1: 整理 分类 | B1: S4 OCOA | C1: OCOA name (CN) | D1: OCOA name (EN)
A2: Term Deposit | B2: 2850010000 | C2: 三个月以内定期存款-RMB-工行 | D2: Non Negotiable TDs =< 90 days, FAM excl
A3: Investment | B3: 1430001010 | C3: 一般交易金融资产-成本-股票 | D3: #N/A
A4: Investment | B4: 1030001010 | C4: 一般交易金融资产-成本-债券 | D4: #N/A
A5: Investment | B5: 1433001010 | C5: 一般交易金融资产-成本-基金 | D5: #N/A
A6: Investment | B6: 1444101500 | C6: 一般交易金融资产-成本-货币式基金 | D6: Money Market Funds (Cash & Cash Equi.)
A7: Investment | B7: 1430001020 | C7: 一般交易金融资产-公允价值变动-股票 | D7: #N/A
A8: Investment | B8: 1030001020 | C8: 一般交易金融资产-公允价值变动-债券 | D8: #N/A
A9: Investment | B9: 1433001020 | C9: 一般交易金融资产-公允价值变动-基金 | D9: #N/A
A10: Investment | B10: 1300000000 | C10: 股票供股权-成本 | D10: Derivatives Assets,Fair Value Option,FAM excl
A11: Investment | B11: 2860011000 | C11: 债券逆回购-面值 | D11: Reverse Repo =< 90 days
A12: Investment | B12: 1143111000 | C12: 债券逆回购-面值 | D12: Reverse Repo >90 days <1 year
A13: Investment | B13: 1143011000 | C13: 债券逆回购-面值 | D13: Reverse Repo >=1 year
A14: Investment | B14: 2860010000 | C14: 债券逆回购-面值 | D14: Reverse Repo =< 90 days, FAM excl
A15: Investment | B15: 1143110000 | C15: 债券逆回购-面值 | D15: Reverse Repo >90 days <1 year, FAM excl
A16: Investment | B16: 1143010000 | C16: 债券逆回购-面值 | D16: Reverse Repo >=1 year, FAM excl
A17: Term Deposit | B17: 1140110000 | C17: 普通定存-一年以下-RMB-工行 | D17: Non Neg TDs > 90 days <1 year, FAM excl
A18: Term Deposit | B18: 1140000000 | C18: 普通定存-一年及以上-RMB-工行 | D18: Long Term Deposits>=1 year, FAM excl
A19: Term Deposit | B19: 114000 待group开code,FAM | C19: 协议定期存款-RMB-工行 | D19: #N/A
A20: Investment | B20: 141000 待Gorup开code,FAM | C20: 可供出售金融资产-成本-股票 | D20: #N/A
A21: Investment | B21: 141000待Gorup开code, FAM | C21: 可供出售金融资产-成本-股票 | D21: #N/A
A22: Investment | B22: 141300 待Gorup开code, FAM | C22: 可供出售金融资产-成本-基金 | D22: #N/A
A23: Investment | B23: 141300待Gorup开code, FAM | C23: 可供出售金融资产-成本-基金 | D23: #N/A
A24: Investment | B24: 1010002000 | C24: 可供出售金融资产-成本-债券 | D24: Available for Sales Securities-NominalVal,FAM excl
A25: Investment | B25: 1444100000 | C25: 可供出售金融资产-成本-货币式基金 | D25: Money Market Funds (Cash & Cash Equiv), FAM excl
A26: Investment | B26: 1444000000 | C26: 可供出售金融资产-成本-货币式基金 | D26: Money Market Funds (Deposits), FAM excl
A27: Investment | B27: 1010002010 | C27: 可供出售金融资产-溢折价摊销-债券 | D27: AFS Securities-Unamort Prem/Disc, FAM excl
A28: Investment | B28: 1010002020 | C28: 可供出售金融资产-公允价值变动-债券 | D28: AFS Securities-Mark to Market change,FAM excl
A29: Investment | B29: 1010002030 | C29: 可供出售金融资产减值准备-债券 | D29: AFS Securities-Prov for Impairment,FAM excl
A30: Investment | B30: 1010000000 | C30: 可供出售金融资产-BOND (IFRS) | D30: Bonds, Available for Sale, FAM excl
A31: Investment | B31: 1000002000 | C31: 持有至到期投资-成本 | D31: Held to Maturity Securities-Nominal Value,FAM excl
A32: Investment | B32: 1000002010 | C32: 持有至到期投资-溢折价摊销 | D32: Held to Maturity Secur-Unamort Prem/Disc,FAM excl
A33: Investment | B33: 1000002020 | C33: 持有至到期投资减值准备 | D33: # 49 OCOA to create in S4 - 11 个保费相关科目，应收保费按按账龄拆分（监管报告），保费收入、预收保费按系统分 （ 对账需求）。 - 17 个投连险账户价值，保户储金及投资款科目：ILP AV roll-forward , 保户储金及投资款-ASO递延收益/万能险账户价值/GUL万能险账户价值… R3 OCOA PH's contract deposits for UL products,Acc.Int.
A34: Insurance cash items | B34: 1243000000 | C34: 保户质押贷款-本金 | D34: Policy Loans
A35: Investment | B35: 1240000000 | C35: 非标投资-本金 | D35: Collateral & Guaranteed Loans, FAM excl
... A41: Investment | B41: 2610000010 | C41: 应收股利-股票股利 | D41: Accrued Investment Income - Dividend
A42: Investment | B42: 260000 待Group开code,FAM | C42: 应收利息-三个月以内定期存款 | D42: #N/A
A43: Investment | B43: 2600000020 | C43: 应收利息-三个月以内定期存款 | D43: Accrued Investments Income, Interest,Bank Interest
A44: Investment | B44: 2600001500 | C44: 应收利息-一般交易性金融资产 | D44: Accrued Investments Income, Interest
A45: Investment | B45: 2600002040 | C45: 应收利息-买入返售金融资产 | D45: Interest Receivable - Reverse Repos, FAM excl
A46: Investment | B46: 2600002041 | C46: 应收利息-买入返售金融资产 | D46: #N/A
A47: Investment | B47: 2600002050 | C47: 应收利息-普通定期存款 | D47: Interest Receivable - Normal Deposits, FAM excl
A48: Investment | B48: 2600002051 | C48: 应收利息-普通定期存款 | D48: #N/A
A49: Investment | B49: 2600002060 | C49: 应收利息-可供出售金融资产 | D49: Interest Receivable - AFS Securities,FAM excl
A50: Investment | B50: 2600002070 | C50: 应收利息-持有至到期金融资产 | D50: Interest Receivable - HTM Securities,FAM excl
A51: Investment | B51: 2600000030 | C51: 应收利息-保户质押贷款 | D51: Accrued Investments Income, Interest, Policy Loan
A52: Investment | B52: 2600002100 | C52: 应收利息-贷款 | D52: Interest Receivable - Loans, LS, FAM excl
A53: Investment | B53: 2600000100 | C53: 应收利息-活期存款 | D53: #N/A
A54: Investment | B54: 2600000000 | C54: 应收利息-FAM (IFRS) | D54: Accrued Investments Income,Interest, FAM excl
A55: Insurance cash items | B55: 2500000000 | C55: 应收保费-IFRS | D55: Due Premium
A56: Insurance cash items | B56: 2500000010 | C56: 应收保费 -3个月以内(含3个月) | D56: #N/A
A57: Insurance cash items | B57: 2500000020 | C57: 应收保费 -3个月至6个月(含6个月) | D57: #N/A
A58: Insurance cash items | B58: 2500000040 | C58: 应收保费 -1年以上 | D58: #N/A
A59: Insurance cash items | B59: 2500000030 | C59: 应收保费 -6个月至1年(含1年) | D59: #N/A
A60: Insurance cash items | B60: 2500000006 | C60: 应收保费(财务) | D60: Insurance receivable - LS/Reg Adj.
A61: Insurance cash items | B61: 2500000060 | C61: 应收保费-短款 | D61: #N/A
A62: Insurance cash items | B62: 2511001500 | C62: 应收分保账款-摊回赔付支出 | D62: Reinsurance Claims Recoverable
A63: Insurance cash items | B63: 2511001501 | C63: 应收分保账款-摊回分保费用 | D63: #N/A
A64: Insurance cash items | B64: 2511001502 | C64: 应收分保账款-纯益手续费 | D64: #N/A
A65: Others | B65: 2501000000 | C65: 其他应收款-保险-退保营销员佣金 | D65: Agent's related Receivables
A66: Others | B66: 2501000001 | C66: 其他应收款-保险-退保手续费 | D66: #N/A
A67: Others | B67: 2501000002 | C67: 其他应收款-保险-退保员工单佣金 | D67: #N/A
A68: Insurance cash items | B68: 2530400050 | C68: 其他应收款-保险-暂存代收保费 | D68: Other receivable - Misc Receivable
A69: Others | B69: 2530401501 | C69: 其他应收款-保险-其他应收 | D69: #N/A
A70: Others | B70: 2530401502 | C70: 其他应收(付)款-保险-应收(付)投资款 | D70: #N/A
A71: Insurance cash items | B71: 2530401500 | C71: 其他应收款-保险-营销员挪用垫付 | D71: Other receivables
A72: Insurance cash items | B72: 2530600010 | C72: 其他应收款-投资合同- 再保 | D72: Financial Reinsurance Receivables
A73: Others | B73: 2711001500 | C73: 其他应收-房屋租赁押金(Non-Intercom) | D73: Other Assets - Real Estate Deposits
A74: Others | B74: 2530401503 | C74: 其他应收款-日常-员工借款 | D74: #N/A
A75: Others | B75: 2530400040 | C75: 其他应收款-日常-其他应收 | D75: Receivables, Others, Other Assets
A76: Others | B76: 2712001500 | C76: 其他应收款-日常-其他押金 | D76: Other Assets - Other Deposits
A77: Others | B77: 2530401504 | C77: 其他应收款-日常- RCE office | D77: #N/A
A78: Others | B78: 2530301500 | C78: 其他应收款-投资-证券清算款 | D78: Receivables, from Sales of Investments
A79: Others | B79: 2530401505 | C79: 其他应收款-投资-其他应收 | D79: #N/A
A80: Investment | B80: 4221000030 | C80: 其他应收-投资-证券清算FX clearing | D80: FX Clearing Account, FAM excl
A81: Investment | B81: 4221001000 | C81: 其他应收-投资-证券清算Suspense | D81: System Interface Suspense
A82: Investment | B82: 4221000100 | C82: 其他应收-投资-证券清算Suspense | D82: Payment request clearing, FAM, OIM
A83: Others | B83: 2530401508 | C83: 其他应收-保险-挂账-银行 | D83: #N/A
A84: Others | B84: 2750010000 | C84: 预付账款-保险-营销员佣金 | D84: Prepaid Commission Reserves
A85: Others | B85: 2700010010 | C85: 预付账款-Citi SF | D85: Prepayment - Service Fee
A86: Others | B86: 2700001500 | C86: 预付账款-保险-其他 | D86: Prepaid Expenses
A87: Others | B87: 2700000001 | C87: 预付账款-日常-固定资产 | D87: #N/A
A88: Others | B88: 2700000002 | C88: 预付账款-日常-其他 | D88: #N/A
A89: Reserves | B89: 3102100000 | C89: 应收分保未到期责任准备金 | D89: Unearned Premium Reserves, Outward
A90: Reserves | B90: 3012000000 | C90: 应收分保未决赔款准备金-已发已报 | D90: Outstanding Claim Reserves, Outward
A91: Reserves | B91: 3032000000 | C91: 应收分保未决赔款准备金-已发未报 | D91: IBNR, Outward
A92: Reserves | B92: 3102000000 | C92: 应收分保寿险责任准备金 | D92: Benefit Reserves, Outward
A93: Reserves | B93: 3102000010 | C93: 应收分保长期健康险责任准备金 | D93: #N/A
A94: Others | B94: 2520001500 | C94: 内部往来-资产-北京 | D94: Receivables, Intercompany
A95: Others | B95: 2520001501 | C95: 关联方往来-AIA HO | D95: #N/A
A96: Others | B96: 2520001502 | C96: 内部往来-保险-北京 | D96: #N/A
A97: Fix asset & Intangible assets | B97: 2014100000 | C97: 机械及动力设备-原值-recon | D97: Other Fixed Assets,-F&E, Costs, Recon
A98: Fix asset & Intangible assets | B98: 2014200000 | C98: 机械及动力设备-累计折旧-recon | D98: Other Fixed Assets, F&E, AccDep, Recon
A99: Fix asset & Intangible assets | B99: 2013100000 | C99: 交通运输设备-原值-recon | D99: Other Fixed Assets, Automobile, Costs, Recon
A100: Fix asset & Intangible assets | B100: 2013200000 | C100: 交通运输设备-累计折旧-recon | D100: Other Fixed Assets, Automobile, Acc Dep, Recon
A101: Fix asset & Intangible assets | B101: 2011100000 | C101: 计算机及辅助设备-原值-recon | D101: Other Fixed Assets, Computer HW, Costs, Recon
A102: Fix asset & Intangible assets | B102: 2011200000 | C102: 计算机及辅助设备-累计折旧-recon | D102: Other Fixed Assets, Computer HW, Acc Dep, Recon
A103: Fix asset & Intangible assets | B103: 2014100030 | C103: 办公设备-家具-原值-recon | D103: #N/A
A104: Fix asset & Intangible assets | B104: 2014200030 | C104: 办公设备-家具-累计折旧-recon | D104: #N/A
A105: Fix asset & Intangible assets | B105: 2790001510 | C105: 固定资产清理-机械及动力设备 | D105: #N/A
...

Sheet Table
A1: Account Category | B1: Value Range | D1: Chart of Accounts | E1: Account Group | F1: From G/L account | G1: To G/L account | H1: Meaning | J1: BPC ByLine (IFRS) | K1: Segment | L1: BPC ByLine (IFRS) Description | M1: IRBY | N1: IRBY name | P1: T1X2 | Q1: T1X2 des | R1: INS/INV
A2: 1. Assets | B2: 100000 – 299999 | D2: AIA | E2: 10 | F2: 100000 | G2: 109999 | H2: 10 Debit Securities | J2: IBY1111 | K2: All | L2: Premium - FY | M2: IRBY1110 | N2: Premium - First Year | P2: CL | Q2: Credit Life | R2: INS
A3: 2. Liabilities | B3: 300000 – 449999 | D3: AIA | E3: 11 | F3: 110000 | G3: 119999 | H3: 11 Deposits and Short Term Inv | J3: IBY1211 | K3: All | L3: Premium - Ren | M3: IRBY1210 | N3: Premium - Renewal | P3: DA | Q3: Pension UL | R3: INS
A4: 3. Equities | B4: 450000 – 499999 | D4: AIA | E4: 12 | F4: 120000 | G4: 129999 | H4: 12 Loans and Receivables | J4: IBY1311 | K4: All | L4: Premium - Single | M4: IRBY1300 | N4: Premium - Single | P4: DB | Q4: Pension ILP | R4: INS
A5: 4. Insurance Revenue | B5: 500000 – 599999 | D5: AIA | E5: 13 | F5: 130000 | G5: 139999 | H5: 13 Derivative Assets | J5: IBY2111 | K5: All | L5: Inward Reins - Premium - First Year | M5: IRBY2100 | N5: Inward reins | P5: DF | Q5: Deferrd Fixed Annuity | R5: INS
A6: 5. Insurance Expenses | B6: 600000 – 699999 | D6: AIA | E6: 14 | F6: 140000 | G6: 149999 | H6: 14 Equity securities | J6: IBY2121 | K6: All | L6: Inward Reins - Premium - Renewal | M6: IRBY2100 | N6: Inward reins | P6: DV | Q6: Deferrd Variable Annuity | R6: INS
A7: 6. Investment Revenue | B7: 700000 – 729999 | D7: AIA | E7: 15 | F7: 150000 | G7: 159999 | H7: 15 Separate & Var acct assets | J7: IBY2131 | K7: All | L7: Inward Reins - Premium - Single | M7: IRBY2100 | N7: Inward reins | P7: FA | Q7: IRS-OL | R7: INS
A8: 7. Gains and Losses | B8: 730000 – 789999 | D8: AIA | E8: 20 | F8: 200000 | G8: 209999 | H8: 20 Property, Plant & Equipment | J8: IBY2211 | K8: All | L8: Outward Reins - First Year | M8: IRBY2200 | N8: Outward reins | P8: GA | Q8: Group Accident | R8: INS
A9: 8. Investment Expenses | B9: 790000 – 791999 | D9: AIA | E9: 21 | F9: 210000 | G9: 219999 | H9: 21 Investment Real Estate | J9: IBY2221 | K9: All | L9: Outward Reins - Renewal | M9: IRBY2200 | N9: Outward reins | P9: GL | Q9: Group Life | R9: INS
A10: 9. Foreign Currency Translation | B10: 798000 – 799999 | D10: AIA | E10: 22 | F10: 220000 | G10: 229999 | H10: 22 Intangible assets | J10: IBY2231 | K10: All | L10: Outward Reins - Single | M10: IRBY2200 | N10: Outward reins | P10: GM | Q10: Group Medical | R10: INS
A11: 10. General and Operating Expenses (GOE) | B11: 800000 – 879999 | D11: AIA | E11: 23 | F11: 230000 | G11: 239999 | H11: 23 Investment in Associates | J11: IBY1121 | K11: All | L11: Premium - FY Due | M11: IRBY1120 | N11: Premium - First Year - Due | P11: GP | Q11: Group Permanent UL | R11: INS
A12: 11. Taxes | B12: 880000 – 889999 | D12: AIA | E12: 24 | F12: 240000 | G12: 249999 | H12: 24 Investment in Subsidiaries | J12: IBY1221 | K12: All | L12: Premium - Ren Due | M12: IRBY1220 | N12: Premium - Renewal - Due | P12: GQ | Q12: Group Permanent ILP | R12: INS
A13: 12. Other Expenses | B13: 890000 – 899999 (Except for 899000) | D13: AIA | E13: 25 | F13: 250000 | G13: 259999 | H13: 25 Trade Receivables | J13: IBY2112 | K13: All | L13: Inward Reins - Profit com - First Year | M13: IRBY2100 | N13: Inward reins | P13: MG | Q13: Mortgage | R13: INS
A14: 13. Dividend to Shareholders | B14: 899000 | D14: AIA | E14: 26 | F14: 260000 | G14: 269999 | H14: 26 Accrued Investment Income | J14: IBY2122 | K14: All | L14: Inward Reins - Profit Commission - Renewal | M14: IRBY2100 | N14: Inward reins | P14: OL | Q14: Ordinary Life | R14: INS
A15: 14. Control and Suspense | B15: 900000 – 999999 | D15: AIA | E15: 27 | F15: 270000 | G15: 279999 | H15: 27 Other Assets | J15: IBY2132 | K15: All | L15: Inward Reins - Profit Commission - Single | M15: IRBY2100 | N15: Inward reins | P15: HN | Q15: HNW-Npar | R15: INS
D16: AIA | E16: 28 | F16: 280000 | G16: 289999 | H16: 28 Cash & cash equivalents | J16: IBY2212 | K16: All | L16: Outward Reins - Profit com - First Year | M16: IRBY2200 | N16: Outward reins | P16: HP | Q16: HNW-par | R16: INS
D17: AIA | E17: 29 | F17: 290000 | G17: 299999 | H17: 29 Assets Held For Sales | J17: IBY2222 | K17: All | L17: Outward Reins - Profit com - Renewal | M17: IRBY2200 | N17: Outward reins | P17: HO | Q17: HNW-par(PH 90%) | R17: INS
D18: AIA | E18: 30 | F18: 300000 | G18: 309999 | H18: 30 Insurance Contracts Liab | J18: IBY2232 | K18: All | L18: Outward Reins - Profit com - Single | M18: IRBY2200 | N18: Outward reins | P18: PA | Q18: Personal Accident | R18: INS
D19: AIA | E19: 31 | F19: 310000 | G19: 319999 | H19: 31 Future Policy Benefit Liab | J19: IBY4111 | K19: All | L19: Change in Insurance Contract Liabilities - Direct | M19: IRBY4110 | N19: Change in insurance contract liabilities | P19: UL | Q19: Universal Life | R19: INS
D20: AIA | E20: 35 | F20: 350000 | G20: 359999 | H20: 35 Policyholders' Contract Dep | J20: IBY2311 | K20: All | L20: Fee Income | M20: IRBY2300 | N20: Expected fee income | P20: UA | Q20: UL-UCX1501 | R20: INS
D21: AIA | E21: 37 | F21: 370000 | G21: 379999 | H21: 37 Other Policyholders' Funds | J21: IBY3411 | K21: All | L21: Surrenders - Direct | M21: IRBY3400 | N21: Surrenders | P21: IL | Q21: Investment Linked | R21: INS
D22: AIA | E22: 38 | F22: 380000 | G22: 399999 | H22: 38 Unearned revenues; reserves | J22: IBY2411 | K22: All | L22: Premium (Reserves) | M22: IRBY2400 | N22: Premium (reserves) | P22: VA | Q22: IRS-UL | R22: INS
D23: AIA | E23: 40 | F23: 400000 | G23: 409999 | H23: 40 Financial Liabilities | J23: IBY2511 | K23: All | L23: Other Revenue | M23: IRBY2500 | N23: Other revenue | P23: OX | Q23: OL PAR | R23: INS
D24: AIA | E24: 41 | F24: 410000 | G24: 419999 | H24: 41 Tax Liabilities | J24: IBY3111 | K24: All | L24: Claims - Direct | M24: IRBY3110 | N24: Claims | P24: OS | Q24: OL PAR(SPE) | R24: INS
D25: AIA | E25: 42 | F25: 420000 | G25: 429999 | H25: 42 Trade & Other Payables | J25: IBY3131 | K25: All | L25: Inward Reins Claims | M25: IRBY3130 | N25: Inward reins. claims | P25: HA | Q25: HNW/HEM-PA | R25: INS
D26: AIA | E26: 43 | F26: 430000 | G26: 439999 | H26: 43 Provisions | J26: IBY4311 | K26: All | L26: Outward Reins. Claims | M26: IRBY4311 | N26: Outward Reins. claims | P26: CK | Q26: Common Stock - offshore (non H share) | R26: INV
D27: AIA | E27: 44 | F27: 440000 | G27: 449999 | H27: 44 Liabilities held for sale | J27: IBY3121 | K27: All | L27: Claims (Reserves) - Direct | M27: IRBY3120 | N27: Claims (reserves) | P27: CA | Q27: Common Stock-A-Share | R27: INV
... D58: AIA | E58: 99 | F58: 990000 | G58: 999999 | H58: 99 Interface Control Accounts | J58: IBY5313 | K58: All | L58: Acq. Exp. Inward - Single | M58: IRBY5310 | N58: Acquisition Exp. - Rein comm | P58: CZ | Q58: Corp/Fixed offshore | R58: INV
J59: IBY5321 | K59: All | L59: Acq. Exp. Outward - First Year | M59: IRBY5310 | N59: Acquisition Exp. - Rein comm | P59: CJ | Q59: Corp/Floating offshore | R59: INV
J60: IBY5322 | K60: All | L60: Acq. Exp. Outward - Renewal | M60: IRBY5310 | N60: Acquisition Exp. - Rein comm | P60: GH | Q60: Government offshore | R60: INV
J61: IBY5323 | K61: All | L61: Acq. Exp. Outward - Single | M61: IRBY5310 | N61: Acquisition Exp. - Rein comm | P61: MI | Q61: Mutual Fund offshore | R61: INV
J62: IBY5211 | K62: All | L62: Acq. Exp. Due/Unearned - First Year | M62: IRBY5210 | N62: Acquisition Exp. - Due | P62: FH | Q62: Financial bond offshore | R62: INV
J63: IBY5212 | K63: All | L63: Acq. Exp. Due/Unearned - Renewal | M63: IRBY5210 | N63: Acquisition Exp. - Due | P63: MO | Q63: Money market fund offshore | R63: INV
J64: IBY5213 | K64: All | L64: Acq. Exp. Due/Unearned - Single | M64: IRBY5210 | N64: Acquisition Exp. - Due | P64: MB | Q64: Mortgage backed security | R64: INV
J65: IBY5411 | K65: All | L65: Change In DAC - Commission - Deferral | M65: IRBY5410 | N65: Change In DAC - commission - deferral | P65: CD | Q65: Negotiable certificates of deposit (同业存单） | R65: INV
J66: IBY5421 | K66: All | L66: Change In DAC - Operating Exps - Deferral | M66: IRBY5420 | N66: Change In DAC - operating exps - deferral | P66: RE | Q66: Real estate debt plan(不动产债权投资计划) | R66: INV
J67: IBY5431 | K67: All | L67: Change In DAC - Comm & Oper Exps - Amort Normal | M67: IRBY5430 | N67: Change In DAC - comm & oper exps - amort. Normal
J68: IBY5441 | K68: All | L68: Change In DAC - Comm & Oper Exps - Amort Others | M68: IRBY5440 | N68: Change In DAC - comm & oper exps - amort. Others
J69: IBY7111 | K69: All | L69: Interest Income | M69: IRBY7110 | N69: Interest Income
J70: IBY0211 | K70: All | L70: Inv Income related to Unit-Linked Contracts | M70: IRBY0210 | N70: Investment income related to Inv-Linked contracts
J71: IBY6221 | K71: All | L71: Finance Costs | M71: IRBY6220 | N71: Finance costs
J72: IBY6222 | K72: All | L72: Repo Interest Expenses | M72: IRBY6220 | N72: Finance costs
J73: IBY8351 | K73: All | L73: Repo Interest Expenses | M73: IRBY8350 | N73: Add: Out-scope Repo interest expense
J74: IBY6231 | K74: All | L74: Repo Interest Expenses | M74: IRBY6230 | N74: Less: Out-scope Repo interest expense
J75: IBY0171 | K75: All | L75: Other Realised Gains/(Loss) | M75: IRBY0170 | N75: Other realised Gains/(Losses)
J76: IBY0151 | K76: All | L76: Net Fair Value Movement Of Derivatives | M76: IRBY0100 | N76: Investment experience for Inv-Linked contracts
J77: IBY7121 | K77: All | L77: Dividend Income | M77: IRBY7120 | N77: Dividend Income - 3rd party
J78: IBY6311 | K78: All | L78: Share of Profit/(Loss) fr Asso. and Joint Ventures | M78: IRBY6310 | N78: Share of P/(L) from associates & joint ventures
... J97: IBY7151 | K97: All | L97: Reversal of Investment Income on Assets Leveraged by Repurchase Agreements | M97: IRBY7150 | N97: Less: Investment income on assets leveraged by repurchase agreements (Out-scope)
J98: IBY0371 | K98: All | L98: LT OPAT - Contra Account | M98: IRBY0370 | N98: #N/A
J99: IBY0181 | K99: All | L99: Net fair value movements of investment properties | M99: IRBY0180 | N99: Net fair value movement of Investment properties
J100: IBY2312 | K100: All | L100: Incremental fee income based on expected AUM | M100: IRBY2300 | N100: Expected fee income
J101: IBY0121 | K101: All | L101: Impairment Of Debt Securities - AFS | M101: IRBY0120 | N101: Impairment of debt securities - AFS
J102: IBY0191 | K102: All | L102: Net fair value movement of own-used properties | M102: IRBY0190 | N102: Revaluation surplus on own-used properties
J103: IBY0381 | K103: All | L103: Net fair value movement of own-used properties | M103: IRBY0380 | N103: Less: Revaluation surplus on own-used properties
J104: IBY6201 | K104: All | L104: Inv Mgt Exp (x Vitality Exp)-Fixed Income & Equity | M104: IRBY6210 | N104: #N/A
J105: IBY0221 | K105: All | L105: Inv Mgmt Exps related to Unit-Linked Contracts | M105: IRBY0220 | N105: Investment management exps related to Inv-Linked contracts
J106: IBY6212 | K106: All | L106: Other Expense - Vitality | M106: IRBY6210 | N106: #N/A
J107: IBY6202 | K107: All | L107: Invest Mgmt Exp (Excl Vitality Exp)-Real Estate | M107: IRBY6210 | N107: #N/A
J108: IBY6011 | K108: All | L108: Permanent Staff | M108: IRBY6110 | N108: Employee benefit expenses
J109: IBY6012 | K109: All | L109: Contract Staff | M109: IRBY6110 | N109: Employee benefit expenses
J110: IBY6055 | K110: All | L110: Other Expenses | M110: IRBY6140 | N110: Other operating expenses
J111: IBY6060 | K111: All | L111: Intercompany Fees - Rent | M111: IRBY6130 | N111: Operating lease rentals (excl amortisation of own-used leasehold land)
J112: IBY6031 | K112: All | L112: Rent and Related Expenses | M112: IRBY6130 | N112: Operating lease rentals (excl amortisation of own-used leasehold land)
J113: IBY6032 | K113: All | L113: Imputed Rent | M113: IRBY6130 | N113: Operating lease rentals (excl amortisation of own-used leasehold land)
J114: IBY6066 | K114: All | L114: Premises related expense (other than rental related cost) | M114: IRBY6140 | N114: Other operating expenses
J115: IBY6054 | K115: All | L115: Office Equipment & Maintenance | M115: IRBY6140 | N115: Other operating expenses
J116: IBY6021 | K116: All | L116: Depreciation For Real Estate/ Furniture and Fixtures/ Leasehold Improvement | M116: IRBY6120 | N116: Depreciation and amortisation (excl depreciation of own-used properties)
J117: IBY0361 | K117: All | L117: Depreciation of property held for use | M117: IRBY0360 | N117: Depreciation and amortisation of own-used properties and own-used leasehold land
J118: IBY6022 | K118: All | L118: Depreciation for Computer Hardware / Software | M118: IRBY6120 | N118: Depreciation and amortisation (excl depreciation of own-used properties)
J119: IBY6023 | K119: All | L119: Other Depreciation | M119: IRBY6120 | N119: Depreciation and amortisation (excl depreciation of own-used properties)
... J154: IBY0711 | K154: All | L154: Non-Controlling Interests | M154: IRBY0710 | N154: Non-controlling interests
J155: IBY0251 | K155: All | L155: Corres. Chg in 3rd Pty Int. in Consol. Inv Funds | M155: IRBY0200 | N155: #N/A
J156: IBY8221 | K156: All | L156: Less: Expected capital appreciation on Equity securities | M156: IRBY8220 | N156: Less: Expected capital appreciation on Equity securities
J157: IBY8251 | K157: All | L157: Less: Expected capital appreciation on investment properties | M157: IRBY8250 | N157: Less: Expected capital appreciation on investment properties
J158: IBY8281 | K158: All | L158: Less: Expected capital appreciation on own-used properties | M158: IRBY8280 | N158: Less: Expected capital appreciation on own-used properties
J159: IBY0151 | K159: All | L159: Net fair value movement of derivatives | M159: IRBY0150 | N159: Net fair value movement of derivatives
J160: IBY8321 | K160: All | L160: Less: Impact from cross currency swap & interest rate swap | M160: IRBY8320 | N160: Less: Impact from cross currency swap & interest rate swap
J161: IBY8341 | K161: All | L161: Add: Investment income on assets leveraged by repurchase agreements (out-scope) | M161: IRBY8340 | N161: Add: Investment income on assets leveraged by repurchase agreements (out-scope)
J162: IBY0111 | K162: All | L162: Net realised Gain/(Losses) from debt securities - AFS after amortisation | M162: IRBY0110 | N162: Net realised Gain/(Losses) from debt securities - AFS after amortisation
J163: IBY0131 | K163: All | L163: Net Gains/(Losses) of debt securities - FVTPL | M163: IRBY0130 | N163: Net Gains/(Losses) of debt securities - FVTPL
J164: IBY0331 | K164: All | L164: Changes in insurance and investment contract liabilities for Policyholders' tax on operating profit before tax | M164: IRBY0330 | N164: Changes in insurance and investment contract liabilities for Policyholders' tax on operating profit before tax
J165: IBY0221 | K165: All | L165: Investment management exps related to Inv-Linked contracts | M165: IRBY0220 | N165: Investment management exps related to Inv-Linked contracts
J166: IBY0251 | K166: All | L166: Corresponding changes in 3rd party interests in consolidated investment funds | M166: IRBY0250 | N166: Corresponding changes in 3rd party interests in consolidated investment funds
J167: IBY0541 | K167: All | L167: Policyholders' tax on non-operating items | M167: IRBY0540 | N167: Policyholders' tax on non-operating items
... J169: IBY6131 | K169: All | L169: Operating lease rentals (excl amortisation of own-used leasehold land) | M169: IRBY6130 | N169: Operating lease rentals (excl amortisation of own-used leasehold land)

Sheet Data-WK
F1: SUN Code | G1: S4 OCOA | H1: A | I1: I
F2: 11030101 | G2: 2850010000 | H2: =[2]!a_eb("CDT,{P1},,2017013,,YA,,,","K=Acc_Code,F={P2},O=B",H$1,$F2) -> #NAME? | I2: =[2]!a_eb("CDT,{P1},,2017013,,YA,,,","K=Acc_Code,F={P2},O=B",I$1,$F2) -> #NAME?
F3: 12010101 | G3: 1430001010 | H3: =[2]!a_eb("CDT,{P1},,2017013,,YA,,,","K=Acc_Code,F={P2},O=B",H$1,$F3) -> #NAME? | I3: =[2]!a_eb("CDT,{P1},,2017013,,YA,,,","K=Acc_Code,F={P2},O=B",I$1,$F3) -> #NAME?
F4: 12010101 | G4: 1030001010 | H4: =[2]!a_eb("CDT,{P1},,2017013,,YA,,,","K=Acc_Code,F={P2},O=B",H$1,$F4) -> #NAME? | I4: =[2]!a_eb("CDT,{P1},,2017013,,YA,,,","K=Acc_Code,F={P2},O=B",I$1,$F4) -> #NAME?
F5: 12010101 | G5: 1433001010 | H5: =[2]!a_eb("CDT,{P1},,2017013,,YA,,,","K=Acc_Code,F={P2},O=B",H$1,$F5) -> #NAME? | I5: =[2]!a_eb("CDT,{P1},,2017013,,YA,,,","K=Acc_Code,F={P2},O=B",I$1,$F5) -> #NAME?
A6: S4 OCOA | B6: 科目代码 | F6: 12010101 | G6: 1444101500 | H6: =[2]!a_eb("CDT,{P1},,2017013,,YA,,,","K=Acc_Code,F={P2},O=B",H$1,$F6) -> #NAME? | I6: =[2]!a_eb("CDT,{P1},,2017013,,YA,,,","K=Acc_Code,F={P2},O=B",I$1,$F6) -> #NAME?
A7: 2800020000 | B7: 110101 | C7: =VLOOKUP(B7,F:G,2,0) -> #N/A | F7: 12010102 | G7: 1430001020 | H7: =[2]!a_eb("CDT,{P1},,2017013,,YA,,,","K=Acc_Code,F={P2},O=B",H$1,$F7) -> #NAME? | I7: =[2]!a_eb("CDT,{P1},,2017013,,YA,,,","K=Acc_Code,F={P2},O=B",I$1,$F7) -> #NAME?
A8: 2800000000 | B8: 110102 | C8: =VLOOKUP(B8,F:G,2,0) -> #N/A | F8: 12010102 | G8: 1030001020 | H8: =[2]!a_eb("CDT,{P1},,2017013,,YA,,,","K=Acc_Code,F={P2},O=B",H$1,$F8) -> #NAME? | I8: =[2]!a_eb("CDT,{P1},,2017013,,YA,,,","K=Acc_Code,F={P2},O=B",I$1,$F8) -> #NAME?
A9: 2800011500 | B9: 110103 | C9: =VLOOKUP(B9,F:G,2,0) -> #N/A | F9: 12010102 | G9: 1433001020 | H9: =[2]!a_eb("CDT,{P1},,2017013,,YA,,,","K=Acc_Code,F={P2},O=B",H$1,$F9) -> #NAME? | I9: =[2]!a_eb("CDT,{P1},,2017013,,YA,,,","K=Acc_Code,F={P2},O=B",I$1,$F9) -> #NAME?
A10: New ICBC CNY 4 | B10: 1102010101 | C10: =VLOOKUP(B10,F:G,2,0) -> #N/A | F10: 12010301 | G10: 1300000000 | H10: =[2]!a_eb("CDT,{P1},,2017013,,YA,,,","K=Acc_Code,F={P2},O=B",H$1,$F10) -> #NAME? | I10: =[2]!a_eb("CDT,{P1},,2017013,,YA,,,","K=Acc_Code,F={P2},O=B",I$1,$F10) -> #NAME?
A11: 2820050200 | B11: 1102010103 | C11: =VLOOKUP(B11,F:G,2,0) -> #N/A | F11: 12030101 | G11: 2860011000 | H11: =[2]!a_eb("CDT,{P1},,2017013,,YA,,,","K=Acc_Code,F={P2},O=B",H$1,$F11) -> #NAME? | I11: =[2]!a_eb("CDT,{P1},,2017013,,YA,,,","K=Acc_Code,F={P2},O=B",I$1,$F11) -> #NAME?
A12: New ICBC CNY 8 | B12: 1102010104 | C12: =VLOOKUP(B12,F:G,2,0) -> #N/A | F12: 12030101 | G12: 1143111000 | H12: =[2]!a_eb("CDT,{P1},,2017013,,YA,,,","K=Acc_Code,F={P2},O=B",H$1,$F12) -> #NAME? | I12: =[2]!a_eb("CDT,{P1},,2017013,,YA,,,","K=Acc_Code,F={P2},O=B",I$1,$F12) -> #NAME?
A13: New ICBC CNY 6 | B13: 1102010106 | C13: =VLOOKUP(B13,F:G,2,0) -> #N/A | F13: 12030101 | G13: 1143011000 | H13: =[2]!a_eb("CDT,{P1},,2017013,,YA,,,","K=Acc_Code,F={P2},O=B",H$1,$F13) -> #NAME? | I13: =[2]!a_eb("CDT,{P1},,2017013,,YA,,,","K=Acc_Code,F={P2},O=B",I$1,$F13) -> #NAME?
A14: New ICBC CNY 13 | B14: 1102010107 | C14: =VLOOKUP(B14,F:G,2,0) -> #N/A | F14: 12030101 | G14: 2860010000 | H14: =[2]!a_eb("CDT,{P1},,2017013,,YA,,,","K=Acc_Code,F={P2},O=B",H$1,$F14) -> #NAME? | I14: =[2]!a_eb("CDT,{P1},,2017013,,YA,,,","K=Acc_Code,F={P2},O=B",I$1,$F14) -> #NAME?
A15: New ICBC CNY 9 | B15: 1102010108 | C15: =VLOOKUP(B15,F:G,2,0) -> #N/A | F15: 12030101 | G15: 1143110000 | H15: =[2]!a_eb("CDT,{P1},,2017013,,YA,,,","K=Acc_Code,F={P2},O=B",H$1,$F15) -> #NAME? | I15: =[2]!a_eb("CDT,{P1},,2017013,,YA,,,","K=Acc_Code,F={P2},O=B",I$1,$F15) -> #NAME?
A16: 2820050000 | B16: 1102010110 | C16: =VLOOKUP(B16,F:G,2,0) -> #N/A | F16: 12030101 | G16: 1143010000 | H16: =[2]!a_eb("CDT,{P1},,2017013,,YA,,,","K=Acc_Code,F={P2},O=B",H$1,$F16) -> #NAME? | I16: =[2]!a_eb("CDT,{P1},,2017013,,YA,,,","K=Acc_Code,F={P2},O=B",I$1,$F16) -> #NAME?
A17: 2820050000 | B17: 1102010111 | C17: =VLOOKUP(B17,F:G,2,0) -> #N/A | F17: 1204010101 | G17: 1140110000 | H17: =[2]!a_eb("CDT,{P1},,2017013,,YA,,,","K=Acc_Code,F={P2},O=B",H$1,$F17) -> #NAME? | I17: =[2]!a_eb("CDT,{P1},,2017013,,YA,,,","K=Acc_Code,F={P2},O=B",I$1,$F17) -> #NAME?
A18: 2820050000 | B18: 1102010112 | C18: =VLOOKUP(B18,F:G,2,0) -> #N/A | F18: 1204020101 | G18: 1140000000 | H18: =[2]!a_eb("CDT,{P1},,2017013,,YA,,,","K=Acc_Code,F={P2},O=B",H$1,$F18) -> #NAME? | I18: =[2]!a_eb("CDT,{P1},,2017013,,YA,,,","K=Acc_Code,F={P2},O=B",I$1,$F18) -> #NAME?
A19: 2820050000 | B19: 1102010113 | C19: =VLOOKUP(B19,F:G,2,0) -> #N/A | F19: 1204030101 | G19: 114000 待group开code,FAM | H19: =[2]!a_eb("CDT,{P1},,2017013,,YA,,,","K=Acc_Code,F={P2},O=B",H$1,$F19) -> #NAME? | I19: =[2]!a_eb("CDT,{P1},,2017013,,YA,,,","K=Acc_Code,F={P2},O=B",I$1,$F19) -> #NAME?
A20: 2820050000 | B20: 1102010114 | C20: =VLOOKUP(B20,F:G,2,0) -> #N/A | F20: 120501 | G20: 141000 待Gorup开code,FAM | H20: =[2]!a_eb("CDT,{P1},,2017013,,YA,,,","K=Acc_Code,F={P2},O=B",H$1,$F20) -> #NAME? | I20: =[2]!a_eb("CDT,{P1},,2017013,,YA,,,","K=Acc_Code,F={P2},O=B",I$1,$F20) -> #NAME?
A21: 2820050000 | B21: 1102010115 | C21: =VLOOKUP(B21,F:G,2,0) -> #N/A | F21: 120501 | G21: 141000待Gorup开code, FAM | H21: =[2]!a_eb("CDT,{P1},,2017013,,YA,,,","K=Acc_Code,F={P2},O=B",H$1,$F21) -> #NAME? | I21: =[2]!a_eb("CDT,{P1},,2017013,,YA,,,","K=Acc_Code,F={P2},O=B",I$1,$F21) -> #NAME?
A22: 2820050000 | B22: 1102010116 | C22: =VLOOKUP(B22,F:G,2,0) -> #N/A | F22: 120501 | G22: 141300 待Gorup开code, FAM | H22: =[2]!a_eb("CDT,{P1},,2017013,,YA,,,","K=Acc_Code,F={P2},O=B",H$1,$F22) -> #NAME? | I22: =[2]!a_eb("CDT,{P1},,2017013,,YA,,,","K=Acc_Code,F={P2},O=B",I$1,$F22) -> #NAME?
A23: New ICBC CNY 3 | B23: 1102010117 | C23: =VLOOKUP(B23,F:G,2,0) -> #N/A | F23: 120501 | G23: 141300待Gorup开code, FAM | H23: =[2]!a_eb("CDT,{P1},,2017013,,YA,,,","K=Acc_Code,F={P2},O=B",H$1,$F23) -> #NAME? | I23: =[2]!a_eb("CDT,{P1},,2017013,,YA,,,","K=Acc_Code,F={P2},O=B",I$1,$F23) -> #NAME?
A24: New ICBC CNY 3 | B24: 1102010122 | C24: =VLOOKUP(B24,F:G,2,0) -> #N/A | F24: 120501 | G24: 1010002000 | H24: =[2]!a_eb("CDT,{P1},,2017013,,YA,,,","K=Acc_Code,F={P2},O=B",H$1,$F24) -> #NAME? | I24: =[2]!a_eb("CDT,{P1},,2017013,,YA,,,","K=Acc_Code,F={P2},O=B",I$1,$F24) -> #NAME?
A25: New ICBC CNY 3 | B25: 1102010124 | C25: =VLOOKUP(B25,F:G,2,0) -> #N/A | F25: 120501 | G25: 1444100000 | H25: =[2]!a_eb("CDT,{P1},,2017013,,YA,,,","K=Acc_Code,F={P2},O=B",H$1,$F25) -> #NAME? | I25: =[2]!a_eb("CDT,{P1},,2017013,,YA,,,","K=Acc_Code,F={P2},O=B",I$1,$F25) -> #NAME?
A26: 2820050000 | B26: 1102010127 | C26: =VLOOKUP(B26,F:G,2,0) -> #N/A | F26: 120501 | G26: 1444000000 | H26: =[2]!a_eb("CDT,{P1},,2017013,,YA,,,","K=Acc_Code,F={P2},O=B",H$1,$F26) -> #NAME? | I26: =[2]!a_eb("CDT,{P1},,2017013,,YA,,,","K=Acc_Code,F={P2},O=B",I$1,$F26) -> #NAME?
A27: New ICBC CNY 5 | B27: 1102010128 | C27: =VLOOKUP(B27,F:G,2,0) -> #N/A | F27: 120502 | G27: 1010002010 | H27: =[2]!a_eb("CDT,{P1},,2017013,,YA,,,","K=Acc_Code,F={P2},O=B",H$1,$F27) -> #NAME? | I27: =[2]!a_eb("CDT,{P1},,2017013,,YA,,,","K=Acc_Code,F={P2},O=B",I$1,$F27) -> #NAME?
A28: 2820050000 | B28: 1102010130 | C28: =VLOOKUP(B28,F:G,2,0) -> #N/A | F28: 120504 | G28: 1010002020 | H28: =[2]!a_eb("CDT,{P1},,2017013,,YA,,,","K=Acc_Code,F={P2},O=B",H$1,$F28) -> #NAME? | I28: =[2]!a_eb("CDT,{P1},,2017013,,YA,,,","K=Acc_Code,F={P2},O=B",I$1,$F28) -> #NAME?
A29: 2820050000 | B29: 1102010131 | C29: =VLOOKUP(B29,F:G,2,0) -> #N/A | F29: 120505 | G29: 1010002030 | H29: =[2]!a_eb("CDT,{P1},,2017013,,YA,,,","K=Acc_Code,F={P2},O=B",H$1,$F29) -> #NAME? | I29: =[2]!a_eb("CDT,{P1},,2017013,,YA,,,","K=Acc_Code,F={P2},O=B",I$1,$F29) -> #NAME?
A30: 2820050000 | B30: 1102010132 | C30: =VLOOKUP(B30,F:G,2,0) -> #N/A | F30: 120506 | G30: 1010000000 | H30: =[2]!a_eb("CDT,{P1},,2017013,,YA,,,","K=Acc_Code,F={P2},O=B",H$1,$F30) -> #NAME? | I30: =[2]!a_eb("CDT,{P1},,2017013,,YA,,,","K=Acc_Code,F={P2},O=B",I$1,$F30) -> #NAME?
A31: 2820050000 | B31: 1102010133 | C31: =VLOOKUP(B31,F:G,2,0) -> #N/A | F31: 120601 | G31: 1000002000 | H31: =[2]!a_eb("CDT,{P1},,2017013,,YA,,,","K=Acc_Code,F={P2},O=B",H$1,$F31) -> #NAME? | I31: =[2]!a_eb("CDT,{P1},,2017013,,YA,,,","K=Acc_Code,F={P2},O=B",I$1,$F31) -> #NAME?
A32: 2820050000 | B32: 1102010135 | C32: =VLOOKUP(B32,F:G,2,0) -> #N/A | F32: 120602 | G32: 1000002010 | H32: =[2]!a_eb("CDT,{P1},,2017013,,YA,,,","K=Acc_Code,F={P2},O=B",H$1,$F32) -> #NAME? | I32: =[2]!a_eb("CDT,{P1},,2017013,,YA,,,","K=Acc_Code,F={P2},O=B",I$1,$F32) -> #NAME?
A33: 2820050000 | B33: 1102010136 | C33: =VLOOKUP(B33,F:G,2,0) -> #N/A | F33: 120604 | G33: 1000002020 | H33: =[2]!a_eb("CDT,{P1},,2017013,,YA,,,","K=Acc_Code,F={P2},O=B",H$1,$F33) -> #NAME? | I33: =[2]!a_eb("CDT,{P1},,2017013,,YA,,,","K=Acc_Code,F={P2},O=B",I$1,$F33) -> #NAME?
A34: New ICBC CNY 4 | B34: 1102010137 | C34: =VLOOKUP(B34,F:G,2,0) -> #N/A | F34: 120701 | G34: 1243000000 | H34: =[2]!a_eb("CDT,{P1},,2017013,,YA,,,","K=Acc_Code,F={P2},O=B",H$1,$F34) -> #NAME? | I34: =[2]!a_eb("CDT,{P1},,2017013,,YA,,,","K=Acc_Code,F={P2},O=B",I$1,$F34) -> #NAME?
A35: New ICBC CNY 6 | B35: 1102010139 | C35: =VLOOKUP(B35,F:G,2,0) -> #N/A | F35: 120801 | G35: 1240000000 | H35: =[2]!a_eb("CDT,{P1},,2017013,,YA,,,","K=Acc_Code,F={P2},O=B",H$1,$F35) -> #NAME? | I35: =[2]!a_eb("CDT,{P1},,2017013,,YA,,,","K=Acc_Code,F={P2},O=B",I$1,$F35) -> #NAME?
A36: New ICBC CNY 4 | B36: 1102010142 | C36: =VLOOKUP(B36,F:G,2,0) -> #N/A | F36: 120801 | G36: 1245002000 | H36: =[2]!a_eb("CDT,{P1},,2017013,,YA,,,","K=Acc_Code,F={P2},O=B",H$1,$F36) -> #NAME? | I36: =[2]!a_eb("CDT,{P1},,2017013,,YA,,,","K=Acc_Code,F={P2},O=B",I$1,$F36) -> #NAME?
A37: 2820050000 | B37: 1102010144 | C37: =VLOOKUP(B37,F:G,2,0) -> #N/A | F37: 121001 | G37: 1430000000 | H37: =[2]!a_eb("CDT,{P1},,2017013,,YA,,,","K=Acc_Code,F={P2},O=B",H$1,$F37) -> #NAME? | I37: =[2]!a_eb("CDT,{P1},,2017013,,YA,,,","K=Acc_Code,F={P2},O=B",I$1,$F37) -> #NAME?
A38: 2820050000 | B38: 1102010147 | C38: =VLOOKUP(B38,F:G,2,0) -> #N/A | F38: 121001 | G38: 1433000000 | H38: =[2]!a_eb("CDT,{P1},,2017013,,YA,,,","K=Acc_Code,F={P2},O=B",H$1,$F38) -> #NAME? | I38: =[2]!a_eb("CDT,{P1},,2017013,,YA,,,","K=Acc_Code,F={P2},O=B",I$1,$F38) -> #NAME?
A39: New ICBC CNY 12 | B39: 1102010148 | C39: =VLOOKUP(B39,F:G,2,0) -> #N/A | F39: 121001 | G39: 1030000000 | H39: =[2]!a_eb("CDT,{P1},,2017013,,YA,,,","K=Acc_Code,F={P2},O=B",H$1,$F39) -> #NAME? | I39: =[2]!a_eb("CDT,{P1},,2017013,,YA,,,","K=Acc_Code,F={P2},O=B",I$1,$F39) -> #NAME?
A40: New ICBC CNY 3 | B40: 1102010151 | C40: =VLOOKUP(B40,F:G,2,0) -> #N/A | F40: 130101 | G40: 2610000000 | H40: =[2]!a_eb("CDT,{P1},,2017013,,YA,,,","K=Acc_Code,F={P2},O=B",H$1,$F40) -> #NAME? | I40: =[2]!a_eb("CDT,{P1},,2017013,,YA,,,","K=Acc_Code,F={P2},O=B",I$1,$F40) -> #NAME?
A41: New ICBC CNY 4 | B41: 1102010156 | C41: =VLOOKUP(B41,F:G,2,0) -> #N/A | F41: 130101 | G41: 2610000010 | H41: =[2]!a_eb("CDT,{P1},,2017013,,YA,,,","K=Acc_Code,F={P2},O=B",H$1,$F41) -> #NAME? | I41: =[2]!a_eb("CDT,{P1},,2017013,,YA,,,","K=Acc_Code,F={P2},O=B",I$1,$F41) -> #NAME?
A42: New ICBC CNY 5 | B42: 1102010157 | C42: =VLOOKUP(B42,F:G,2,0) -> #N/A | F42: 130301 | G42: 260000 待Group开code,FAM | H42: =[2]!a_eb("CDT,{P1},,2017013,,YA,,,","K=Acc_Code,F={P2},O=B",H$1,$F42) -> #NAME? | I42: =[2]!a_eb("CDT,{P1},,2017013,,YA,,,","K=Acc_Code,F={P2},O=B",I$1,$F42) -> #NAME?
A43: New ICBC CNY 6 | B43: 1102010158 | C43: =VLOOKUP(B43,F:G,2,0) -> #N/A | F43: 130301 | G43: 2600000020 | H43: =[2]!a_eb("CDT,{P1},,2017013,,YA,,,","K=Acc_Code,F={P2},O=B",H$1,$F43) -> #NAME? | I43: =[2]!a_eb("CDT,{P1},,2017013,,YA,,,","K=Acc_Code,F={P2},O=B",I$1,$F43) -> #NAME?
A44: New ICBC CNY 7 | B44: 1102010159 | C44: =VLOOKUP(B44,F:G,2,0) -> #N/A | F44: 130302 | G44: 2600001500 | H44: =[2]!a_eb("CDT,{P1},,2017013,,YA,,,","K=Acc_Code,F={P2},O=B",H$1,$F44) -> #NAME? | I44: =[2]!a_eb("CDT,{P1},,2017013,,YA,,,","K=Acc_Code,F={P2},O=B",I$1,$F44) -> #NAME?
A45: New ICBC CNY 8 | B45: 1102010160 | C45: =VLOOKUP(B45,F:G,2,0) -> #N/A | F45: 130304 | G45: 2600002040 | H45: =[2]!a_eb("CDT,{P1},,2017013,,YA,,,","K=Acc_Code,F={P2},O=B",H$1,$F45) -> #NAME? | I45: =[2]!a_eb("CDT,{P1},,2017013,,YA,,,","K=Acc_Code,F={P2},O=B",I$1,$F45) -> #NAME?
A46: New ICBC CNY 7 | B46: 1102010161 | C46: =VLOOKUP(B46,F:G,2,0) -> #N/A | F46: 130304 | G46: 2600002041 | H46: =[2]!a_eb("CDT,{P1},,2017013,,YA,,,","K=Acc_Code,F={P2},O=B",H$1,$F46) -> #NAME? | I46: =[2]!a_eb("CDT,{P1},,2017013,,YA,,,","K=Acc_Code,F={P2},O=B",I$1,$F46) -> #NAME?
A47: New ICBC CNY 11 | B47: 1102010163 | C47: =VLOOKUP(B47,F:G,2,0) -> #N/A | F47: 130305 | G47: 2600002050 | H47: =[2]!a_eb("CDT,{P1},,2017013,,YA,,,","K=Acc_Code,F={P2},O=B",H$1,$F47) -> #NAME? | I47: =[2]!a_eb("CDT,{P1},,2017013,,YA,,,","K=Acc_Code,F={P2},O=B",I$1,$F47) -> #NAME?
A48: New ICBC CNY 4 | B48: 1102010164 | C48: =VLOOKUP(B48,F:G,2,0) -> #N/A | F48: 130305 | G48: 2600002051 | H48: =[2]!a_eb("CDT,{P1},,2017013,,YA,,,","K=Acc_Code,F={P2},O=B",H$1,$F48) -> #NAME? | I48: =[2]!a_eb("CDT,{P1},,2017013,,YA,,,","K=Acc_Code,F={P2},O=B",I$1,$F48) -> #NAME?
A49: New ICBC CNY 5 | B49: 1102010165 | C49: =VLOOKUP(B49,F:G,2,0) -> #N/A | F49: 130308 | G49: 2600002060 | H49: =[2]!a_eb("CDT,{P1},,2017013,,YA,,,","K=Acc_Code,F={P2},O=B",H$1,$F49) -> #NAME? | I49: =[2]!a_eb("CDT,{P1},,2017013,,YA,,,","K=Acc_Code,F={P2},O=B",I$1,$F49) -> #NAME?
A50: New ICBC CNY 14 | B50: 1102010166 | C50: =VLOOKUP(B50,F:G,2,0) -> #N/A | F50: 130309 | G50: 2600002070 | H50: =[2]!a_eb("CDT,{P1},,2017013,,YA,,,","K=Acc_Code,F={P2},O=B",H$1,$F50) -> #NAME? | I50: =[2]!a_eb("CDT,{P1},,2017013,,YA,,,","K=Acc_Code,F={P2},O=B",I$1,$F50) -> #NAME?
A51: New ICBC CNY 7 | B51: 1102010167 | C51: =VLOOKUP(B51,F:G,2,0) -> #N/A | F51: 130310 | G51: 2600000030 | H51: =[2]!a_eb("CDT,{P1},,2017013,,YA,,,","K=Acc_Code,F={P2},O=B",H$1,$F51) -> #NAME? | I51: =[2]!a_eb("CDT,{P1},,2017013,,YA,,,","K=Acc_Code,F={P2},O=B",I$1,$F51) -> #NAME?
A52: New ICBC CNY 5 | B52: 1102010168 | C52: =VLOOKUP(B52,F:G,2,0) -> #N/A | F52: 130311 | G52: 2600002100 | H52: =[2]!a_eb("CDT,{P1},,2017013,,YA,,,","K=Acc_Code,F={P2},O=B",H$1,$F52) -> #NAME? | I52: =[2]!a_eb("CDT,{P1},,2017013,,YA,,,","K=Acc_Code,F={P2},O=B",I$1,$F52) -> #NAME?
A53: New ICBC CNY 4 | B53: 1102010169 | C53: =VLOOKUP(B53,F:G,2,0) -> #N/A | F53: 130313 | G53: 2600000100 | H53: =[2]!a_eb("CDT,{P1},,2017013,,YA,,,","K=Acc_Code,F={P2},O=B",H$1,$F53) -> #NAME? | I53: =[2]!a_eb("CDT,{P1},,2017013,,YA,,,","K=Acc_Code,F={P2},O=B",I$1,$F53) -> #NAME?
A54: New ICBC CNY 6 | B54: 1102010170 | C54: =VLOOKUP(B54,F:G,2,0) -> #N/A | F54: 130315 | G54: 2600000000 | H54: =[2]!a_eb("CDT,{P1},,2017013,,YA,,,","K=Acc_Code,F={P2},O=B",H$1,$F54) -> #NAME? | I54: =[2]!a_eb("CDT,{P1},,2017013,,YA,,,","K=Acc_Code,F={P2},O=B",I$1,$F54) -> #NAME?
A55: To close | B55: 1102010171 | C55: =VLOOKUP(B55,F:G,2,0) -> #N/A | F55: 13040101 | G55: 2500000000 | H55: =[2]!a_eb("CDT,{P1},,2017013,,YA,,,","K=Acc_Code,F={P2},O=B",H$1,$F55) -> #NAME? | I55: =[2]!a_eb("CDT,{P1},,2017013,,YA,,,","K=Acc_Code,F={P2},O=B",I$1,$F55) -> #NAME?
A56: 2820050200 | B56: 1102010172 | C56: =VLOOKUP(B56,F:G,2,0) -> #N/A | F56: 13040101 | G56: 2500000010 | H56: =[2]!a_eb("CDT,{P1},,2017013,,YA,,,","K=Acc_Code,F={P2},O=B",H$1,$F56) -> #NAME? | I56: =[2]!a_eb("CDT,{P1},,2017013,,YA,,,","K=Acc_Code,F={P2},O=B",I$1,$F56) -> #NAME?
A57: 2820050200 | B57: 1102010173 | C57: =VLOOKUP(B57,F:G,2,0) -> #N/A | F57: 13040102 | G57: 2500000020 | H57: =[2]!a_eb("CDT,{P1},,2017013,,YA,,,","K=Acc_Code,F={P2},O=B",H$1,$F57) -> #NAME? | I57: =[2]!a_eb("CDT,{P1},,2017013,,YA,,,","K=Acc_Code,F={P2},O=B",I$1,$F57) -> #NAME?
A58: 2820050200 | B58: 1102010174 | C58: =VLOOKUP(B58,F:G,2,0) -> #N/A | F58: 13040104 | G58: 2500000030 | H58: =[2]!a_eb("CDT,{P1},,2017013,,YA,,,","K=Acc_Code,F={P2},O=B",H$1,$F58) -> #NAME? | I58: =[2]!a_eb("CDT,{P1},,2017013,,YA,,,","K=Acc_Code,F={P2},O=B",I$1,$F58) -> #NAME?
A59: 2820050200 | B59: 1102010175 | C59: =VLOOKUP(B59,F:G,2,0) -> #N/A | F59: 13040103 | G59: 2500000040 | H59: =[2]!a_eb("CDT,{P1},,2017013,,YA,,,","K=Acc_Code,F={P2},O=B",H$1,$F59) -> #NAME? | I59: =[2]!a_eb("CDT,{P1},,2017013,,YA,,,","K=Acc_Code,F={P2},O=B",I$1,$F59) -> #NAME?
A60: 2820050200 | B60: 1102010176 | C60: =VLOOKUP(B60,F:G,2,0) -> #N/A | F60: 130402 | G60: 2500000006 | H60: =[2]!a_eb("CDT,{P1},,2017013,,YA,,,","K=Acc_Code,F={P2},O=B",H$1,$F60) -> #NAME? | I60: =[2]!a_eb("CDT,{P1},,2017013,,YA,,,","K=Acc_Code,F={P2},O=B",I$1,$F60) -> #NAME?
A61: 2820050200 | B61: 1102010177 | C61: =VLOOKUP(B61,F:G,2,0) -> #N/A | F61: 130404 | G61: 2500000060 | H61: =[2]!a_eb("CDT,{P1},,2017013,,YA,,,","K=Acc_Code,F={P2},O=B",H$1,$F61) -> #NAME? | I61: =[2]!a_eb("CDT,{P1},,2017013,,YA,,,","K=Acc_Code,F={P2},O=B",I$1,$F61) -> #NAME?
A62: 2820050200 | B62: 1102010178 | C62: =VLOOKUP(B62,F:G,2,0) -> #N/A | F62: 130502 | G62: 2511001500 | H62: =[2]!a_eb("CDT,{P1},,2017013,,YA,,,","K=Acc_Code,F={P2},O=B",H$1,$F62) -> #NAME? | I62: =[2]!a_eb("CDT,{P1},,2017013,,YA,,,","K=Acc_Code,F={P2},O=B",I$1,$F62) -> #NAME?
A63: 2820050200 | B63: 1102010179 | C63: =VLOOKUP(B63,F:G,2,0) -> #N/A | F63: 130503 | G63: 2511001501 | H63: =[2]!a_eb("CDT,{P1},,2017013,,YA,,,","K=Acc_Code,F={P2},O=B",H$1,$F63) -> #NAME? | I63: =[2]!a_eb("CDT,{P1},,2017013,,YA,,,","K=Acc_Code,F={P2},O=B",I$1,$F63) -> #NAME?
A64: New ICBC CNY 6 | B64: 1102010182 | C64: =VLOOKUP(B64,F:G,2,0) -> #N/A | F64: 130504 | G64: 2511001502 | H64: =[2]!a_eb("CDT,{P1},,2017013,,YA,,,","K=Acc_Code,F={P2},O=B",H$1,$F64) -> #NAME? | I64: =[2]!a_eb("CDT,{P1},,2017013,,YA,,,","K=Acc_Code,F={P2},O=B",I$1,$F64) -> #NAME?
A65: New ICBC CNY 7 | B65: 1102010183 | C65: =VLOOKUP(B65,F:G,2,0) -> #N/A | F65: 13060101 | G65: 2501000000 | H65: =[2]!a_eb("CDT,{P1},,2017013,,YA,,,","K=Acc_Code,F={P2},O=B",H$1,$F65) -> #NAME? | I65: =[2]!a_eb("CDT,{P1},,2017013,,YA,,,","K=Acc_Code,F={P2},O=B",I$1,$F65) -> #NAME?
A66: New ICBC CNY 10 | B66: 1102010184 | C66: =VLOOKUP(B66,F:G,2,0) -> #N/A | F66: 13060102 | G66: 2501000001 | H66: =[2]!a_eb("CDT,{P1},,2017013,,YA,,,","K=Acc_Code,F={P2},O=B",H$1,$F66) -> #NAME? | I66: =[2]!a_eb("CDT,{P1},,2017013,,YA,,,","K=Acc_Code,F={P2},O=B",I$1,$F66) -> #NAME?
A67: 2820050200 | B67: 1102010186 | C67: =VLOOKUP(B67,F:G,2,0) -> #N/A | F67: 13060103 | G67: 2501000002 | H67: =[2]!a_eb("CDT,{P1},,2017013,,YA,,,","K=Acc_Code,F={P2},O=B",H$1,$F67) -> #NAME? | I67: =[2]!a_eb("CDT,{P1},,2017013,,YA,,,","K=Acc_Code,F={P2},O=B",I$1,$F67) -> #NAME?
A68: 2820050000 | B68: 1102010187 | C68: =VLOOKUP(B68,F:G,2,0) -> #N/A | F68: 13060105 | G68: 2530400050 | H68: =[2]!a_eb("CDT,{P1},,2017013,,YA,,,","K=Acc_Code,F={P2},O=B",H$1,$F68) -> #NAME? | I68: =[2]!a_eb("CDT,{P1},,2017013,,YA,,,","K=Acc_Code,F={P2},O=B",I$1,$F68) -> #NAME?
A69: 2820050200 | B69: 1102010188 | C69: =VLOOKUP(B69,F:G,2,0) -> #N/A | F69: 13060106 | G69: 2530401501 | H69: =[2]!a_eb("CDT,{P1},,2017013,,YA,,,","K=Acc_Code,F={P2},O=B",H$1,$F69) -> #NAME? | I69: =[2]!a_eb("CDT,{P1},,2017013,,YA,,,","K=Acc_Code,F={P2},O=B",I$1,$F69) -> #NAME?
A70: 2820050000 | B70: 1102010189 | C70: =VLOOKUP(B70,F:G,2,0) -> #N/A | F70: 13060108 | G70: 2530401502 | H70: =[2]!a_eb("CDT,{P1},,2017013,,YA,,,","K=Acc_Code,F={P2},O=B",H$1,$F70) -> #NAME? | I70: =[2]!a_eb("CDT,{P1},,2017013,,YA,,,","K=Acc_Code,F={P2},O=B",I$1,$F70) -> #NAME?
A71: New ICBC CNY 3 | B71: 1102010192 | C71: =VLOOKUP(B71,F:G,2,0) -> #N/A | F71: 13060110 | G71: 2530401500 | H71: =[2]!a_eb("CDT,{P1},,2017013,,YA,,,","K=Acc_Code,F={P2},O=B",H$1,$F71) -> #NAME? | I71: =[2]!a_eb("CDT,{P1},,2017013,,YA,,,","K=Acc_Code,F={P2},O=B",I$1,$F71) -> #NAME?
A72: 2820050000 | B72: 1102010197 | C72: =VLOOKUP(B72,F:G,2,0) -> #N/A | F72: 13060111 | G72: 2530600010 | H72: =[2]!a_eb("CDT,{P1},,2017013,,YA,,,","K=Acc_Code,F={P2},O=B",H$1,$F72) -> #NAME? | I72: =[2]!a_eb("CDT,{P1},,2017013,,YA,,,","K=Acc_Code,F={P2},O=B",I$1,$F72) -> #NAME?
A73: New ICBC CNY 5 | B73: 1102010198 | C73: =VLOOKUP(B73,F:G,2,0) -> #N/A | F73: 13060301 | G73: 2711001500 | H73: =[2]!a_eb("CDT,{P1},,2017013,,YA,,,","K=Acc_Code,F={P2},O=B",H$1,$F73) -> #NAME? | I73: =[2]!a_eb("CDT,{P1},,2017013,,YA,,,","K=Acc_Code,F={P2},O=B",I$1,$F73) -> #NAME?
A74: 2820050000 | B74: 1102010199 | C74: =VLOOKUP(B74,F:G,2,0) -> #N/A | F74: 13060302 | G74: 2530401503 | H74: =[2]!a_eb("CDT,{P1},,2017013,,YA,,,","K=Acc_Code,F={P2},O=B",H$1,$F74) -> #NAME? | I74: =[2]!a_eb("CDT,{P1},,2017013,,YA,,,","K=Acc_Code,F={P2},O=B",I$1,$F74) -> #NAME?
A75: New ICBC CNY 3 | B75: 11020101A1 | C75: =VLOOKUP(B75,F:G,2,0) -> #N/A | F75: 13060304 | G75: 2530400040 | H75: =[2]!a_eb("CDT,{P1},,2017013,,YA,,,","K=Acc_Code,F={P2},O=B",H$1,$F75) -> #NAME? | I75: =[2]!a_eb("CDT,{P1},,2017013,,YA,,,","K=Acc_Code,F={P2},O=B",I$1,$F75) -> #NAME?
A76: 2820050200 | B76: 11020101A2 | C76: =VLOOKUP(B76,F:G,2,0) -> #N/A | F76: 13060307 | G76: 2712001500 | H76: =[2]!a_eb("CDT,{P1},,2017013,,YA,,,","K=Acc_Code,F={P2},O=B",H$1,$F76) -> #NAME? | I76: =[2]!a_eb("CDT,{P1},,2017013,,YA,,,","K=Acc_Code,F={P2},O=B",I$1,$F76) -> #NAME?
A77: New ICBC CNY 3 | B77: 11020101A3 | C77: =VLOOKUP(B77,F:G,2,0) -> #N/A | F77: 13060309 | G77: 2530401504 | H77: =[2]!a_eb("CDT,{P1},,2017013,,YA,,,","K=Acc_Code,F={P2},O=B",H$1,$F77) -> #NAME? | I77: =[2]!a_eb("CDT,{P1},,2017013,,YA,,,","K=Acc_Code,F={P2},O=B",I$1,$F77) -> #NAME?
A78: 2820050200 | B78: 11020101A4 | C78: =VLOOKUP(B78,F:G,2,0) -> #N/A | F78: 13060401 | G78: 2530301500 | H78: =[2]!a_eb("CDT,{P1},,2017013,,YA,,,","K=Acc_Code,F={P2},O=B",H$1,$F78) -> #NAME? | I78: =[2]!a_eb("CDT,{P1},,2017013,,YA,,,","K=Acc_Code,F={P2},O=B",I$1,$F78) -> #NAME?
A79: 2820050200 | B79: 11020101A5 | C79: =VLOOKUP(B79,F:G,2,0) -> #N/A | F79: 13060402 | G79: 2530401505 | H79: =[2]!a_eb("CDT,{P1},,2017013,,YA,,,","K=Acc_Code,F={P2},O=B",H$1,$F79) -> #NAME? | I79: =[2]!a_eb("CDT,{P1},,2017013,,YA,,,","K=Acc_Code,F={P2},O=B",I$1,$F79) -> #NAME?
A80: 2820050200 | B80: 11020101A6 | C80: =VLOOKUP(B80,F:G,2,0) -> #N/A | F80: 13060404 | G80: 4221000030 | H80: =[2]!a_eb("CDT,{P1},,2017013,,YA,,,","K=Acc_Code,F={P2},O=B",H$1,$F80) -> #NAME? | I80: =[2]!a_eb("CDT,{P1},,2017013,,YA,,,","K=Acc_Code,F={P2},O=B",I$1,$F80) -> #NAME?
A81: 2820050000 | B81: 11020101A7 | C81: =VLOOKUP(B81,F:G,2,0) -> #N/A | F81: 13060405 | G81: 4221001000 | H81: =[2]!a_eb("CDT,{P1},,2017013,,YA,,,","K=Acc_Code,F={P2},O=B",H$1,$F81) -> #NAME? | I81: =[2]!a_eb("CDT,{P1},,2017013,,YA,,,","K=Acc_Code,F={P2},O=B",I$1,$F81) -> #NAME?
A82: 2820050200 | B82: 11020101A8 | C82: =VLOOKUP(B82,F:G,2,0) -> #N/A | F82: 13060405 | G82: 4221000100 | H82: =[2]!a_eb("CDT,{P1},,2017013,,YA,,,","K=Acc_Code,F={P2},O=B",H$1,$F82) -> #NAME? | I82: =[2]!a_eb("CDT,{P1},,2017013,,YA,,,","K=Acc_Code,F={P2},O=B",I$1,$F82) -> #NAME?
A83: 2820050000 | B83: 11020101A9 | C83: =VLOOKUP(B83,F:G,2,0) -> #N/A | F83: 13060501 | G83: 2530401508 | H83: =[2]!a_eb("CDT,{P1},,2017013,,YA,,,","K=Acc_Code,F={P2},O=B",H$1,$F83) -> #NAME? | I83: =[2]!a_eb("CDT,{P1},,2017013,,YA,,,","K=Acc_Code,F={P2},O=B",I$1,$F83) -> #NAME?
A84: 2820050200 | B84: 11020101B0 | C84: =VLOOKUP(B84,F:G,2,0) -> #N/A | F84: 13070101 | G84: 2750010000 | H84: =[2]!a_eb("CDT,{P1},,2017013,,YA,,,","K=Acc_Code,F={P2},O=B",H$1,$F84) -> #NAME? | I84: =[2]!a_eb("CDT,{P1},,2017013,,YA,,,","K=Acc_Code,F={P2},O=B",I$1,$F84) -> #NAME?
A85: 2820050000 | B85: 11020101B1 | C85: =VLOOKUP(B85,F:G,2,0) -> #N/A | F85: 13070106 | G85: 2700010010 | H85: =[2]!a_eb("CDT,{P1},,2017013,,YA,,,","K=Acc_Code,F={P2},O=B",H$1,$F85) -> #NAME? | I85: =[2]!a_eb("CDT,{P1},,2017013,,YA,,,","K=Acc_Code,F={P2},O=B",I$1,$F85) -> #NAME?
A86: 2820050000 | B86: 11020101B2 | C86: =VLOOKUP(B86,F:G,2,0) -> #N/A | F86: 13070100 | G86: 2700001500 | H86: =[2]!a_eb("CDT,{P1},,2017013,,YA,,,","K=Acc_Code,F={P2},O=B",H$1,$F86) -> #NAME? | I86: =[2]!a_eb("CDT,{P1},,2017013,,YA,,,","K=Acc_Code,F={P2},O=B",I$1,$F86) -> #NAME?
A87: 2820050000 | B87: 11020101B3 | C87: =VLOOKUP(B87,F:G,2,0) -> #N/A | F87: 13070201 | G87: 2700000001 | H87: =[2]!a_eb("CDT,{P1},,2017013,,YA,,,","K=Acc_Code,F={P2},O=B",H$1,$F87) -> #NAME? | I87: =[2]!a_eb("CDT,{P1},,2017013,,YA,,,","K=Acc_Code,F={P2},O=B",I$1,$F87) -> #NAME?
A88: New ABC CNY 4 | B88: 1102010201 | C88: =VLOOKUP(B88,F:G,2,0) -> #N/A | F88: 13070200 | G88: 2700000002 | H88: =[2]!a_eb("CDT,{P1},,2017013,,YA,,,","K=Acc_Code,F={P2},O=B",H$1,$F88) -> #NAME? | I88: =[2]!a_eb("CDT,{P1},,2017013,,YA,,,","K=Acc_Code,F={P2},O=B",I$1,$F88) -> #NAME?
A89: New ABC CNY 4 | B89: 1102010223 | C89: =VLOOKUP(B89,F:G,2,0) -> #N/A | F89: 140101 | G89: 3102100000 | H89: =[2]!a_eb("CDT,{P1},,2017013,,YA,,,","K=Acc_Code,F={P2},O=B",H$1,$F89) -> #NAME? | I89: =[2]!a_eb("CDT,{P1},,2017013,,YA,,,","K=Acc_Code,F={P2},O=B",I$1,$F89) -> #NAME?
A90: New ABC CNY 5 | B90: 1102010224 | C90: =VLOOKUP(B90,F:G,2,0) -> #N/A | F90: 14020101 | G90: 3012000000 | H90: =[2]!a_eb("CDT,{P1},,2017013,,YA,,,","K=Acc_Code,F={P2},O=B",H$1,$F90) -> #NAME? | I90: =[2]!a_eb("CDT,{P1},,2017013,,YA,,,","K=Acc_Code,F={P2},O=B",I$1,$F90) -> #NAME?
A91: New ABC CNY 4 | B91: 1102010225 | C91: =VLOOKUP(B91,F:G,2,0) -> #N/A | F91: 14020201 | G91: 3032000000 | H91: =[2]!a_eb("CDT,{P1},,2017013,,YA,,,","K=Acc_Code,F={P2},O=B",H$1,$F91) -> #NAME? | I91: =[2]!a_eb("CDT,{P1},,2017013,,YA,,,","K=Acc_Code,F={P2},O=B",I$1,$F91) -> #NAME?
A92: New ABC CNY 3 | B92: 1102010229 | C92: =VLOOKUP(B92,F:G,2,0) -> #N/A | F92: 140302 | G92: 3102000000 | H92: =[2]!a_eb("CDT,{P1},,2017013,,YA,,,","K=Acc_Code,F={P2},O=B",H$1,$F92) -> #NAME? | I92: =[2]!a_eb("CDT,{P1},,2017013,,YA,,,","K=Acc_Code,F={P2},O=B",I$1,$F92) -> #NAME?
A93: New ABC CNY 3 | B93: 1102010230 | C93: =VLOOKUP(B93,F:G,2,0) -> #N/A | F93: 140402 | G93: 3102000010 | H93: =[2]!a_eb("CDT,{P1},,2017013,,YA,,,","K=Acc_Code,F={P2},O=B",H$1,$F93) -> #NAME? | I93: =[2]!a_eb("CDT,{P1},,2017013,,YA,,,","K=Acc_Code,F={P2},O=B",I$1,$F93) -> #NAME?
A94: New ABC CNY 4 | B94: 1102010232 | C94: =VLOOKUP(B94,F:G,2,0) -> #N/A | F94: 150101 | G94: 2520001500 | H94: =[2]!a_eb("CDT,{P1},,2017013,,YA,,,","K=Acc_Code,F={P2},O=B",H$1,$F94) -> #NAME? | I94: =[2]!a_eb("CDT,{P1},,2017013,,YA,,,","K=Acc_Code,F={P2},O=B",I$1,$F94) -> #NAME?
A95: New ABC CNY 3 | B95: 1102010233 | C95: =VLOOKUP(B95,F:G,2,0) -> #N/A | F95: 150301 | G95: 2520001501 | H95: =[2]!a_eb("CDT,{P1},,2017013,,YA,,,","K=Acc_Code,F={P2},O=B",H$1,$F95) -> #NAME? | I95: =[2]!a_eb("CDT,{P1},,2017013,,YA,,,","K=Acc_Code,F={P2},O=B",I$1,$F95) -> #NAME?
A96: New ABC CNY 3 | B96: 1102010234 | C96: =VLOOKUP(B96,F:G,2,0) -> #N/A | F96: 150501 | G96: 2520001502 | H96: =[2]!a_eb("CDT,{P1},,2017013,,YA,,,","K=Acc_Code,F={P2},O=B",H$1,$F96) -> #NAME? | I96: =[2]!a_eb("CDT,{P1},,2017013,,YA,,,","K=Acc_Code,F={P2},O=B",I$1,$F96) -> #NAME?
A97: New ABC CNY 3 | B97: 1102010235 | C97: =VLOOKUP(B97,F:G,2,0) -> #N/A | F97: 16020201 | G97: 2014100000 | H97: =[2]!a_eb("CDT,{P1},,2017013,,YA,,,","K=Acc_Code,F={P2},O=B",H$1,$F97) -> #NAME? | I97: =[2]!a_eb("CDT,{P1},,2017013,,YA,,,","K=Acc_Code,F={P2},O=B",I$1,$F97) -> #NAME?
A98: New ABC CNY 3 | B98: 1102010236 | C98: =VLOOKUP(B98,F:G,2,0) -> #N/A | F98: 16020202 | G98: 2014200000 | H98: =[2]!a_eb("CDT,{P1},,2017013,,YA,,,","K=Acc_Code,F={P2},O=B",H$1,$F98) -> #NAME? | I98: =[2]!a_eb("CDT,{P1},,2017013,,YA,,,","K=Acc_Code,F={P2},O=B",I$1,$F98) -> #NAME?
A99: New ABC CNY 3 | B99: 1102010237 | C99: =VLOOKUP(B99,F:G,2,0) -> #N/A | F99: 16020301 | G99: 2013100000 | H99: =[2]!a_eb("CDT,{P1},,2017013,,YA,,,","K=Acc_Code,F={P2},O=B",H$1,$F99) -> #NAME? | I99: =[2]!a_eb("CDT,{P1},,2017013,,YA,,,","K=Acc_Code,F={P2},O=B",I$1,$F99) -> #NAME?
... A104: New BOC CNY 4 | B104: 1102010304 | C104: =VLOOKUP(B104,F:G,2,0) -> #N/A | F104: 16020502 | G104: 2014200030 | H104: =[2]!a_eb("CDT,{P1},,2017013,,YA,,,","K=Acc_Code,F={P2},O=B",H$1,$F104) -> #NAME? | I104: =[2]!a_eb("CDT,{P1},,2017013,,YA,,,","K=Acc_Code,F={P2},O=B",I$1,$F104) -> #NAME?
...

Sheet IFRS only
A1: SUN Code
A2: 120506 | B2: =VLOOKUP(A2,'V1'!E:E,1,0) -> 120506
A3: 121001 | B3: =VLOOKUP(A3,'V1'!E:E,1,0) -> 121001
A4: 130315 | B4: =VLOOKUP(A4,'V1'!E:E,1,0) -> 130315
A5: 13070106 | B5: =VLOOKUP(A5,'V1'!E:E,1,0) -> 13070106
A6: 16050501 | B6: =VLOOKUP(A6,'V1'!E:E,1,0) -> 16050501
A7: 16050502 | B7: =VLOOKUP(A7,'V1'!E:E,1,0) -> 16050502
A8: 160001 | B8: =VLOOKUP(A8,'V1'!E:E,1,0) -> 160001
A9: 160002 | B9: =VLOOKUP(A9,'V1'!E:E,1,0) -> 160002
A10: 160003 | B10: =VLOOKUP(A10,'V1'!E:E,1,0) -> 160003
A11: 160004 | B11: =VLOOKUP(A11,'V1'!E:E,1,0) -> 160004
A12: 160005 | B12: =VLOOKUP(A12,'V1'!E:E,1,0) -> 160005
A13: 160006 | B13: =VLOOKUP(A13,'V1'!E:E,1,0) -> 160006
... A73: 550203 | B73: =VLOOKUP(A73,'V1'!E:E,1,0) -> 550203

Sheet ETL Scope
A1: ACCT_CD | B1: AMOUNT | C1: IFRS_CD | D1: BYLINE_CD | F1: Row Labels | G1: Sum of AMOUNT | I1: Row Labels | J1: Sum of AMOUNT
A2: 3710000000 | B2: -185807 | C2: IS02000000 | D2: IBY0000 | F2: 2201000000 | G2: 15661221387 | I2: 2201000000 | J2: 15661221387 | K2: =VLOOKUP(I2,'Data-WK'!A:B,2,0) -> 160001
A3: 6700000000 | B3: 0 | C3: IS05082000 | D3: IBY5411 | F3: 2201000010 | G3: 32296507 | I3: 2201000010 | J3: 32296507 | K3: =VLOOKUP(I3,'Data-WK'!A:B,2,0) -> 160005
A4: 5010100000 | B4: 0 | C4: IS04010000 | D4: IBY1221 | F4: 2201000030 | G4: 49205146 | I4: 2201000030 | J4: 49205146 | K4: =VLOOKUP(I4,'Data-WK'!A:B,2,0) -> 160003
A5: 6700400000 | B5: 0 | C5: IS05082000 | D5: IBY5411 | F5: 2201200030 | G5: -15126751 | I5: 2201200030 | J5: -15126751 | K5: =VLOOKUP(I5,'Data-WK'!A:B,2,0) -> 160004
A6: 4203000000 | B6: 0 | C6: IS02081100 | D6: IBY0000 | F6: 2201300000 | G6: 49088979 | I6: 2201300000 | J6: 49088979 | K6: =VLOOKUP(I6,'Data-WK'!A:B,2,0) -> 160007
A7: 6700200000 | B7: 0 | C7: IS05082000 | D7: IBY5431 | F7: 2201400000 | G7: 134968552 | I7: 2201400000 | J7: 134968552 | K7: =VLOOKUP(I7,'Data-WK'!A:B,2,0) -> 160008
A8: 3103000000 | B8: 0 | C8: IS02000000 | D8: IBY0000 | F8: 2203000000 | G8: 12049381 | I8: 2203000000 | J8: 12049381 | K8: =VLOOKUP(I8,'Data-WK'!A:B,2,0) -> 160002
A9: 6700100000 | B9: 0 | C9: IS05082000 | D9: IBY5421 | F9: 2203000010 | G9: 3244274 | I9: 2203000010 | J9: 3244274 | K9: =VLOOKUP(I9,'Data-WK'!A:B,2,0) -> 160006
A10: 4203000000 | B10: 0 | C10: IS02081100 | D10: IBY0000 | F10: 2500000000 | G10: 1912514542 | I10: 2500000000 | J10: 1912514542 | K10: =VLOOKUP(I10,'Data-WK'!A:B,2,0) -> 13040101
A11: 6700400000 | B11: 0 | C11: IS05082000 | D11: IBY5411 | F11: 2750010000 | G11: 1592476 | I11: 2750010000 | J11: 1592476 | K11: =VLOOKUP(I11,'Data-WK'!A:B,2,0) -> 13070101
A12: 5010000000 | B12: 0 | C12: IS04010000 | D12: IBY1121 | F12: 3030000000 | G12: -489209887 | I12: 3030000000 | J12: -489209887 | K12: =VLOOKUP(I12,'Data-WK'!A:B,2,0) -> 22020201
A13: 4203000000 | B13: 0 | C13: IS02081100 | D13: IBY0000 | F13: 3032000000 | G13: 180946158 | I13: 3032000000 | J13: 180946158 | K13: =VLOOKUP(I13,'Data-WK'!A:B,2,0) -> 14020201
... A61: 3102000000 | B61: 0 | C61: IS01060000 | D61: IBY0000 | F61: 6700700000 | G61: -120980350 | I61: 6700700000 | J61: -120980350 | K61: =VLOOKUP(I61,'Data-WK'!A:B,2,0) -> 5106050510
A62: 6700200000 | B62: 0 | C62: IS05082000 | D62: IBY5431 | F62: (blank) | I62: (blank)
A63: 2500000000 | B63: 0 | C63: IS01220000 | D63: IBY0000 | F63: Grand Total | G63: 0 | I63: Grand Total | J63: 0
A64: 4203000000 | B64: 0 | C64: IS02081100 | D64: IBY0000
A65: 6700700000 | B65: 0 | C65: IS05082000 | D65: IBY5431
A66: 6700500000 | B66: 0 | C66: IS05082000 | D66: IBY5411
A67: 5052010000 | B67: 0 | C67: IS04010000 | D67: IBY2411
A68: 2203000000 | B68: 0 | C68: IS01070000 | D68: IBY0000
A69: 6700000000 | B69: 0 | C69: IS05082000 | D69: IBY5411
A70: 3800000000 | B70: 0 | C70: IS02000000 | D70: IBY0000
A71: 6104001000 | B71: -114928 | C71: IS05031000 | D71: IBY4111
A72: 5010000000 | B72: 0 | C72: IS04010000 | D72: IBY1121
A73: 6102000000 | B73: 0 | C73: IS05040000 | D73: IBY4313
A74: 5010000010 | B74: 0 | C74: IS04010000 | D74: IBY1121
A75: 6700200000 | B75: 0 | C75: IS05082000 | D75: IBY5431
... A7947: 5010100000 | B7947: -614189 | C7947: IS04010000 | D7947: IBY1221
